[
    {
        "hanzi":"理家",
        "pinyin":"lǐjiā"
    },
    {
        "hanzi":"利权",
        "pinyin":"lìquán"
    },
    {
        "hanzi":"粮区",
        "pinyin":"liángqū"
    },
    {
        "hanzi":"两党制",
        "pinyin":"liǎngdǎngzhì"
    },
    {
        "hanzi":"列位",
        "pinyin":"lièwèi"
    },
    {
        "hanzi":"零担",
        "pinyin":"língdàn"
    },
    {
        "hanzi":"领花",
        "pinyin":"lǐnghuā"
    },
    {
        "hanzi":"领水",
        "pinyin":"lǐngshuǐ"
    },
    {
        "hanzi":"溜冰鞋",
        "pinyin":"liūbīngxié"
    },
    {
        "hanzi":"流盼",
        "pinyin":"liúpàn"
    },
    {
        "hanzi":"满仓",
        "pinyin":"mǎncāng"
    },
    {
        "hanzi":"流失率",
        "pinyin":"liúshīlǜ"
    },
    {
        "hanzi":"流食",
        "pinyin":"liúshí"
    },
    {
        "hanzi":"碌碡",
        "pinyin":"liùzhou"
    },
    {
        "hanzi":"拢共",
        "pinyin":"lǒnggòng"
    },
    {
        "hanzi":"露富",
        "pinyin":"lòufù"
    },
    {
        "hanzi":"庐山真面目",
        "pinyin":"lúshānzhēnmiànmù"
    },
    {
        "hanzi":"略图",
        "pinyin":"lüètú"
    },
    {
        "hanzi":"瘰疬",
        "pinyin":"luǒlì"
    },
    {
        "hanzi":"猫儿眼",
        "pinyin":"māoryǎn"
    },
    {
        "hanzi":"毛蓝",
        "pinyin":"máolán"
    },
    {
        "hanzi":"锚泊",
        "pinyin":"máobó"
    },
    {
        "hanzi":"锚固",
        "pinyin":"máogù"
    },
    {
        "hanzi":"门斗",
        "pinyin":"méndǒu"
    },
    {
        "hanzi":"蒙哄",
        "pinyin":"ménghǒng"
    },
    {
        "hanzi":"盟书",
        "pinyin":"méngshū"
    },
    {
        "hanzi":"猛男",
        "pinyin":"měngnán"
    },
    {
        "hanzi":"米糕",
        "pinyin":"mǐgāo"
    },
    {
        "hanzi":"秘宝",
        "pinyin":"mìbǎo"
    },
    {
        "hanzi":"面软",
        "pinyin":"miànruǎn"
    },
    {
        "hanzi":"邈远",
        "pinyin":"miǎoyuǎn"
    },
    {
        "hanzi":"命在旦夕",
        "pinyin":"mìngzàidànxī"
    },
    {
        "hanzi":"摸奖",
        "pinyin":"mōjiǎng"
    },
    {
        "hanzi":"磨砂玻璃",
        "pinyin":"móshābōli"
    },
    {
        "hanzi":"墨斗鱼",
        "pinyin":"mòdǒuyú"
    },
    {
        "hanzi":"墨晶",
        "pinyin":"mòjīng"
    },
    {
        "hanzi":"墨渍",
        "pinyin":"mòzì"
    },
    {
        "hanzi":"牧主",
        "pinyin":"mùzhǔ"
    },
    {
        "hanzi":"闹灾",
        "pinyin":"nàozāi"
    },
    {
        "hanzi":"内陆湖",
        "pinyin":"nèilùhú"
    },
    {
        "hanzi":"能掐会算",
        "pinyin":"néngqiāhuìsuàn"
    },
    {
        "hanzi":"尼龙布",
        "pinyin":"nílóngbù"
    },
    {
        "hanzi":"黏度",
        "pinyin":"niándù"
    },
    {
        "hanzi":"黏着",
        "pinyin":"niánzhuó"
    },
    {
        "hanzi":"镍币",
        "pinyin":"nièbì"
    },
    {
        "hanzi":"农机站",
        "pinyin":"nóngjīzhàn"
    },
    {
        "hanzi":"暖水壶",
        "pinyin":"nuǎnshuǐhú"
    },
    {
        "hanzi":"挪借",
        "pinyin":"nuójiè"
    },
    {
        "hanzi":"糯稻",
        "pinyin":"nuòdào"
    },
    {
        "hanzi":"攀扯",
        "pinyin":"pānchě"
    },
    {
        "hanzi":"捧杀",
        "pinyin":"pěngshā"
    },
    {
        "hanzi":"皮带轮",
        "pinyin":"pídàilún"
    },
    {
        "hanzi":"品第",
        "pinyin":"pǐndì"
    },
    {
        "hanzi":"普快",
        "pinyin":"pǔkuài"
    },
    {
        "hanzi":"骑马找马",
        "pinyin":"qímǎzhǎomǎ"
    },
    {
        "hanzi":"气根",
        "pinyin":"qìgēn"
    },
    {
        "hanzi":"契据",
        "pinyin":"qìjù"
    },
    {
        "hanzi":"千里驹",
        "pinyin":"qiānlǐjū"
    },
    {
        "hanzi":"峭立",
        "pinyin":"qiàolì"
    },
    {
        "hanzi":"青冢",
        "pinyin":"qīngzhǒng"
    },
    {
        "hanzi":"清汤寡水",
        "pinyin":"qīngtāngguǎshuǐ"
    },
    {
        "hanzi":"清馨",
        "pinyin":"qīngxīn"
    },
    {
        "hanzi":"秋游",
        "pinyin":"qiūyóu"
    },
    {
        "hanzi":"曲别针",
        "pinyin":"qūbiézhēn"
    },
    {
        "hanzi":"驱逐令",
        "pinyin":"qūzhúlìng"
    },
    {
        "hanzi":"去污粉",
        "pinyin":"qùwūfěn"
    },
    {
        "hanzi":"全武行",
        "pinyin":"quánwǔháng"
    },
    {
        "hanzi":"缺门",
        "pinyin":"quēmén"
    },
    {
        "hanzi":"热得快",
        "pinyin":"rèdekuài"
    },
    {
        "hanzi":"认贼作父",
        "pinyin":"rènzéizuòfù"
    },
    {
        "hanzi":"溶蚀",
        "pinyin":"róngshí"
    },
    {
        "hanzi":"肉孜节",
        "pinyin":"ròuzījié"
    },
    {
        "hanzi":"如隔三秋",
        "pinyin":"rúgésānqiū"
    },
    {
        "hanzi":"如芒在背",
        "pinyin":"rúmángzàibèi"
    },
    {
        "hanzi":"锐眼",
        "pinyin":"ruìyǎn"
    },
    {
        "hanzi":"撒酒疯",
        "pinyin":"sājiǔfēng"
    },
    {
        "hanzi":"塞牙",
        "pinyin":"sāiyá"
    },
    {
        "hanzi":"三八妇女节",
        "pinyin":"sānbāfùnǚjié"
    },
    {
        "hanzi":"三花脸",
        "pinyin":"sānhuāliǎn"
    },
    {
        "hanzi":"沙碛",
        "pinyin":"shāqì"
    },
    {
        "hanzi":"傻瓜相机",
        "pinyin":"shǎguāxiàngjī"
    },
    {
        "hanzi":"扇坠",
        "pinyin":"shànzhuì"
    },
    {
        "hanzi":"烧心",
        "pinyin":"shāoxīn"
    },
    {
        "hanzi":"少白头",
        "pinyin":"shàobáitóu"
    },
    {
        "hanzi":"蛇蜕",
        "pinyin":"shétuì"
    },
    {
        "hanzi":"生理盐水",
        "pinyin":"shēnglǐyánshuǐ"
    },
    {
        "hanzi":"生荣死哀",
        "pinyin":"shēngróngsǐ'āi"
    },
    {
        "hanzi":"绳墨",
        "pinyin":"shéngmò"
    },
    {
        "hanzi":"失墒",
        "pinyin":"shīshāng"
    },
    {
        "hanzi":"失贞",
        "pinyin":"shīzhēn"
    },
    {
        "hanzi":"石笔",
        "pinyin":"shíbǐ"
    },
    {
        "hanzi":"市制",
        "pinyin":"shìzhì"
    },
    {
        "hanzi":"试场",
        "pinyin":"shìchǎng"
    },
    {
        "hanzi":"柿霜",
        "pinyin":"shìshuāng"
    },
    {
        "hanzi":"手写体",
        "pinyin":"shǒuxiětǐ"
    },
    {
        "hanzi":"熟土",
        "pinyin":"shútǔ"
    },
    {
        "hanzi":"暑伏",
        "pinyin":"shǔfú"
    },
    {
        "hanzi":"数词",
        "pinyin":"shùcí"
    },
    {
        "hanzi":"双肩挑",
        "pinyin":"shuāngjiāntiāo"
    },
    {
        "hanzi":"双响",
        "pinyin":"shuāngxiǎng"
    },
    {
        "hanzi":"水洗布",
        "pinyin":"shuǐxǐbù"
    },
    {
        "hanzi":"税案",
        "pinyin":"shuì'àn"
    },
    {
        "hanzi":"顺意",
        "pinyin":"shùnyì"
    },
    {
        "hanzi":"司库",
        "pinyin":"sīkù"
    },
    {
        "hanzi":"司药",
        "pinyin":"sīyào"
    },
    {
        "hanzi":"官媒",
        "pinyin":"guānméi"
    },
    {
        "hanzi":"撕肝裂肺",
        "pinyin":"sīgānlièfèi"
    },
    {
        "hanzi":"死读书",
        "pinyin":"sǐdúshū"
    },
    {
        "hanzi":"松烟",
        "pinyin":"sōngyān"
    },
    {
        "hanzi":"素愿",
        "pinyin":"sùyuàn"
    },
    {
        "hanzi":"随风倒",
        "pinyin":"suífēngdǎo"
    },
    {
        "hanzi":"胎发",
        "pinyin":"tāifà"
    },
    {
        "hanzi":"台鉴",
        "pinyin":"táijiàn"
    },
    {
        "hanzi":"抬头纹",
        "pinyin":"táitóuwén"
    },
    {
        "hanzi":"弹簧门",
        "pinyin":"tánhuángmén"
    },
    {
        "hanzi":"碳黑",
        "pinyin":"tànhēi"
    },
    {
        "hanzi":"天差地远",
        "pinyin":"tiānchādìyuǎn"
    },
    {
        "hanzi":"填方",
        "pinyin":"tiánfāng"
    },
    {
        "hanzi":"挑错儿",
        "pinyin":"tiāocuòr"
    },
    {
        "hanzi":"跳房子",
        "pinyin":"tiàofángzi"
    },
    {
        "hanzi":"跳皮筋儿",
        "pinyin":"tiàopíjīnr"
    },
    {
        "hanzi":"贴本儿",
        "pinyin":"tiēběnr"
    },
    {
        "hanzi":"通览",
        "pinyin":"tōnglǎn"
    },
    {
        "hanzi":"通权达变",
        "pinyin":"tōngquándábiàn"
    },
    {
        "hanzi":"偷营",
        "pinyin":"tōuyíng"
    },
    {
        "hanzi":"徒托空言",
        "pinyin":"tútuōkōngyán"
    },
    {
        "hanzi":"土名",
        "pinyin":"tǔmíng"
    },
    {
        "hanzi":"土腥气",
        "pinyin":"tǔxīngqì"
    },
    {
        "hanzi":"兔唇",
        "pinyin":"tùchún"
    },
    {
        "hanzi":"团籍",
        "pinyin":"tuánjí"
    },
    {
        "hanzi":"团圆节",
        "pinyin":"tuányuánjié"
    },
    {
        "hanzi":"颓靡",
        "pinyin":"tuímǐ"
    },
    {
        "hanzi":"拖堂",
        "pinyin":"tuōtáng"
    },
    {
        "hanzi":"脱胶",
        "pinyin":"tuōjiāo"
    },
    {
        "hanzi":"脱漏",
        "pinyin":"tuōlòu"
    },
    {
        "hanzi":"脱卸",
        "pinyin":"tuōxiè"
    },
    {
        "hanzi":"袜筒",
        "pinyin":"wàtǒng"
    },
    {
        "hanzi":"弯度",
        "pinyin":"wāndù"
    },
    {
        "hanzi":"弯头",
        "pinyin":"wāntóu"
    },
    {
        "hanzi":"丸剂",
        "pinyin":"wánjì"
    },
    {
        "hanzi":"玩儿完",
        "pinyin":"wánrwán"
    },
    {
        "hanzi":"婉顺",
        "pinyin":"wǎnshùn"
    },
    {
        "hanzi":"万能胶",
        "pinyin":"wànnéngjiāo"
    },
    {
        "hanzi":"委培",
        "pinyin":"wěipéi"
    },
    {
        "hanzi":"温课",
        "pinyin":"wēnkè"
    },
    {
        "hanzi":"文契",
        "pinyin":"wénqì"
    },
    {
        "hanzi":"文胸",
        "pinyin":"wénxiōng"
    },
    {
        "hanzi":"窝工",
        "pinyin":"wōgōng"
    },
    {
        "hanzi":"诬指",
        "pinyin":"wūzhǐ"
    },
    {
        "hanzi":"无头苍蝇",
        "pinyin":"wútóucāngying"
    },
    {
        "hanzi":"芜菁",
        "pinyin":"wújīng"
    },
    {
        "hanzi":"五方杂处",
        "pinyin":"wǔfāngzáchǔ"
    },
    {
        "hanzi":"舞迷",
        "pinyin":"wǔmí"
    },
    {
        "hanzi":"雾茫茫",
        "pinyin":"wùmángmáng"
    },
    {
        "hanzi":"吸顶灯",
        "pinyin":"xīdǐngdēng"
    },
    {
        "hanzi":"吸墨纸",
        "pinyin":"xīmòzhǐ"
    },
    {
        "hanzi":"析疑",
        "pinyin":"xīyí"
    },
    {
        "hanzi":"洗发精",
        "pinyin":"xǐfàjīng"
    },
    {
        "hanzi":"下车伊始",
        "pinyin":"xiàchēyīshǐ"
    },
    {
        "hanzi":"下聘",
        "pinyin":"xiàpìn"
    },
    {
        "hanzi":"衔冤",
        "pinyin":"xiányuān"
    },
    {
        "hanzi":"现成饭",
        "pinyin":"xiànchéngfàn"
    },
    {
        "hanzi":"馅儿饼",
        "pinyin":"xiànrbǐng"
    },
    {
        "hanzi":"香橙",
        "pinyin":"xiāngchéng"
    },
    {
        "hanzi":"香肚",
        "pinyin":"xiāngdǔ"
    },
    {
        "hanzi":"湘菜",
        "pinyin":"xiāngcài"
    },
    {
        "hanzi":"消声器",
        "pinyin":"xiāoshēngqì"
    },
    {
        "hanzi":"消歇",
        "pinyin":"xiāoxiē"
    },
    {
        "hanzi":"萧规曹随",
        "pinyin":"xiāoguīcáosuí"
    },
    {
        "hanzi":"小别",
        "pinyin":"xiǎobié"
    },
    {
        "hanzi":"晓以利害",
        "pinyin":"xiǎoyǐlìhài"
    },
    {
        "hanzi":"写家",
        "pinyin":"xiějiā"
    },
    {
        "hanzi":"血糊糊",
        "pinyin":"xiěhūhū"
    },
    {
        "hanzi":"泻肚子",
        "pinyin":"xièdùzi"
    },
    {
        "hanzi":"信筒",
        "pinyin":"xìntǒng"
    },
    {
        "hanzi":"行李房",
        "pinyin":"xínglifáng"
    },
    {
        "hanzi":"醒木",
        "pinyin":"xǐngmù"
    },
    {
        "hanzi":"凶耗",
        "pinyin":"xiōnghào"
    },
    {
        "hanzi":"凶宅",
        "pinyin":"xiōngzhái"
    },
    {
        "hanzi":"胸膜炎",
        "pinyin":"xiōngmóyán"
    },
    {
        "hanzi":"雄视",
        "pinyin":"xióngshì"
    },
    {
        "hanzi":"休怪",
        "pinyin":"xiūguài"
    },
    {
        "hanzi":"秀挺",
        "pinyin":"xiùtǐng"
    },
    {
        "hanzi":"袖珍本",
        "pinyin":"xiùzhēnběn"
    },
    {
        "hanzi":"虚飘飘",
        "pinyin":"xūpiāopiāo"
    },
    {
        "hanzi":"玄之又玄",
        "pinyin":"xuánzhīyòuxuán"
    },
    {
        "hanzi":"削肩",
        "pinyin":"xuējiān"
    },
    {
        "hanzi":"穴播",
        "pinyin":"xuébō"
    },
    {
        "hanzi":"寻章摘句",
        "pinyin":"xúnzhāngzhāijù"
    },
    {
        "hanzi":"压车",
        "pinyin":"yāchē"
    },
    {
        "hanzi":"咽喉炎",
        "pinyin":"yānhóuyán"
    },
    {
        "hanzi":"妍丽",
        "pinyin":"yánlì"
    },
    {
        "hanzi":"盐滩",
        "pinyin":"yántān"
    },
    {
        "hanzi":"演期",
        "pinyin":"yǎnqī"
    },
    {
        "hanzi":"唁函",
        "pinyin":"yànhán"
    },
    {
        "hanzi":"验钞机",
        "pinyin":"yànchāojī"
    },
    {
        "hanzi":"养眼",
        "pinyin":"yǎngyǎn"
    },
    {
        "hanzi":"妖风",
        "pinyin":"yāofēng"
    },
    {
        "hanzi":"摇笔杆儿",
        "pinyin":"yáobǐgǎnr"
    },
    {
        "hanzi":"摇唇鼓舌",
        "pinyin":"yáochúngǔshé"
    },
    {
        "hanzi":"咬舌",
        "pinyin":"yǎoshé"
    },
    {
        "hanzi":"夜光表",
        "pinyin":"yèguāngbiǎo"
    },
    {
        "hanzi":"一得之见",
        "pinyin":"yīdézhījiàn"
    },
    {
        "hanzi":"一锅端",
        "pinyin":"yīguōduān"
    },
    {
        "hanzi":"一叶知秋",
        "pinyin":"yīyèzhīqiū"
    },
    {
        "hanzi":"异日",
        "pinyin":"yìrì"
    },
    {
        "hanzi":"薏米",
        "pinyin":"yìmǐ"
    },
    {
        "hanzi":"殷富",
        "pinyin":"yīnfù"
    },
    {
        "hanzi":"撞脸",
        "pinyin":"zhuàngliǎn"
    },
    {
        "hanzi":"淫亵",
        "pinyin":"yínxiè"
    },
    {
        "hanzi":"荫翳",
        "pinyin":"yìnyì"
    },
    {
        "hanzi":"英年",
        "pinyin":"yīngnián"
    },
    {
        "hanzi":"痈疽",
        "pinyin":"yōngjū"
    },
    {
        "hanzi":"幽婉",
        "pinyin":"yōuwǎn"
    },
    {
        "hanzi":"余风",
        "pinyin":"yúfēng"
    },
    {
        "hanzi":"余勇可贾",
        "pinyin":"yúyǒngkěgǔ"
    },
    {
        "hanzi":"羽纱",
        "pinyin":"yǔshā"
    },
    {
        "hanzi":"驭手",
        "pinyin":"yùshǒu"
    },
    {
        "hanzi":"欲壑难填",
        "pinyin":"yùhènántián"
    },
    {
        "hanzi":"圆钢",
        "pinyin":"yuángāng"
    },
    {
        "hanzi":"云崖",
        "pinyin":"yúnyá"
    },
    {
        "hanzi":"臧否",
        "pinyin":"zāngpǐ"
    },
    {
        "hanzi":"藏袍",
        "pinyin":"zàngpáo"
    },
    {
        "hanzi":"早搏",
        "pinyin":"zǎobó"
    },
    {
        "hanzi":"早造",
        "pinyin":"zǎozào"
    },
    {
        "hanzi":"藻饰",
        "pinyin":"zǎoshì"
    },
    {
        "hanzi":"择友",
        "pinyin":"zéyǒu"
    },
    {
        "hanzi":"沾花惹草",
        "pinyin":"zhānhuārěcǎo"
    },
    {
        "hanzi":"谵妄",
        "pinyin":"zhānwàng"
    },
    {
        "hanzi":"战争贩子",
        "pinyin":"zhànzhēngfànzi"
    },
    {
        "hanzi":"招眼",
        "pinyin":"zhāoyǎn"
    },
    {
        "hanzi":"找米下锅",
        "pinyin":"zhǎomǐxiàguō"
    },
    {
        "hanzi":"找平",
        "pinyin":"zhǎopíng"
    },
    {
        "hanzi":"找窍门",
        "pinyin":"zhǎoqiàomén"
    },
    {
        "hanzi":"折叠床",
        "pinyin":"zhédiéchuáng"
    },
    {
        "hanzi":"诊疗所",
        "pinyin":"zhěnliáosuǒ"
    },
    {
        "hanzi":"争嘴",
        "pinyin":"zhēngzuǐ"
    },
    {
        "hanzi":"征引",
        "pinyin":"zhēngyǐn"
    },
    {
        "hanzi":"职务工资",
        "pinyin":"zhíwùgōngzī"
    },
    {
        "hanzi":"旨要",
        "pinyin":"zhǐyào"
    },
    {
        "hanzi":"中提琴",
        "pinyin":"zhōngtíqín"
    },
    {
        "hanzi":"钟鼎文",
        "pinyin":"zhōngdǐngwén"
    },
    {
        "hanzi":"猪倌儿",
        "pinyin":"zhūguānr"
    },
    {
        "hanzi":"竹箱",
        "pinyin":"zhúxiāng"
    },
    {
        "hanzi":"助桀为虐",
        "pinyin":"zhùjiéwéinüè"
    },
    {
        "hanzi":"著作人",
        "pinyin":"zhùzuòrén"
    },
    {
        "hanzi":"抓差",
        "pinyin":"zhuāchāi"
    },
    {
        "hanzi":"撞骗",
        "pinyin":"zhuàngpiàn"
    },
    {
        "hanzi":"撞针",
        "pinyin":"zhuàngzhēn"
    },
    {
        "hanzi":"追缉",
        "pinyin":"zhuījī"
    }
]