[
  {
    "hanzi": "浆洗",
    "pinyin": "jiāngxǐ"
  },
  {
    "hanzi": "讲情面",
    "pinyin": "jiǎngqíngmiàn"
  },
  {
    "hanzi": "交公",
    "pinyin": "jiāogōng"
  },
  {
    "hanzi": "狡狯",
    "pinyin": "jiǎokuài"
  },
  {
    "hanzi": "校订",
    "pinyin": "jiàodìng"
  },
  {
    "hanzi": "校阅",
    "pinyin": "jiàoyuè"
  },
  {
    "hanzi": "节操",
    "pinyin": "jiécāo"
  },
  {
    "hanzi": "金丹",
    "pinyin": "jīndān"
  },
  {
    "hanzi": "绝笔",
    "pinyin": "juébǐ"
  },
  {
    "hanzi": "开架",
    "pinyin": "kāijià"
  },
  {
    "hanzi": "开释",
    "pinyin": "kāishì"
  },
  {
    "hanzi": "勘探队",
    "pinyin": "kāntànduì"
  },
  {
    "hanzi": "叩击",
    "pinyin": "kòujī"
  },
  {
    "hanzi": "扣帽子",
    "pinyin": "kòumàozi"
  },
  {
    "hanzi": "宽以待人",
    "pinyin": "kuānyǐdàirén"
  },
  {
    "hanzi": "岿然",
    "pinyin": "kuīrán"
  },
  {
    "hanzi": "来日方长",
    "pinyin": "láirìfāngcháng"
  },
  {
    "hanzi": "冷然",
    "pinyin": "lěngrán"
  },
  {
    "hanzi": "力挫",
    "pinyin": "lìcuò"
  },
  {
    "hanzi": "料事如神",
    "pinyin": "liàoshìrúshén"
  },
  {
    "hanzi": "榴弹",
    "pinyin": "liúdàn"
  },
  {
    "hanzi": "漏电",
    "pinyin": "lòudiàn"
  },
  {
    "hanzi": "路轨",
    "pinyin": "lùguǐ"
  },
  {
    "hanzi": "卖关子",
    "pinyin": "màiguānzi"
  },
  {
    "hanzi": "满腹经纶",
    "pinyin": "mǎnfùjīnglún"
  },
  {
    "hanzi": "绵密",
    "pinyin": "miánmì"
  },
  {
    "hanzi": "面筋",
    "pinyin": "miànjin"
  },
  {
    "hanzi": "民族自决权",
    "pinyin": "mínzúzìjuéquán"
  },
  {
    "hanzi": "木屐",
    "pinyin": "mùjī"
  },
  {
    "hanzi": "闹笑话",
    "pinyin": "nàoxiàohua"
  },
  {
    "hanzi": "逆水",
    "pinyin": "nìshuǐ"
  },
  {
    "hanzi": "排头",
    "pinyin": "páitóu"
  },
  {
    "hanzi": "牌局",
    "pinyin": "páijú"
  },
  {
    "hanzi": "判案",
    "pinyin": "pàn'àn"
  },
  {
    "hanzi": "胖墩儿",
    "pinyin": "pàngdūnr"
  },
  {
    "hanzi": "配伍",
    "pinyin": "pèiwǔ"
  },
  {
    "hanzi": "批办",
    "pinyin": "pībàn"
  },
  {
    "hanzi": "骈文",
    "pinyin": "piánwén"
  },
  {
    "hanzi": "嫔妃",
    "pinyin": "pínfēi"
  },
  {
    "hanzi": "漆黑一团",
    "pinyin": "qīhēiyītuán"
  },
  {
    "hanzi": "齐步走",
    "pinyin": "qíbùzǒu"
  },
  {
    "hanzi": "祈望",
    "pinyin": "qíwàng"
  },
  {
    "hanzi": "强心剂",
    "pinyin": "qiángxīnjì"
  },
  {
    "hanzi": "窃国",
    "pinyin": "qièguó"
  },
  {
    "hanzi": "琴师",
    "pinyin": "qínshī"
  },
  {
    "hanzi": "情夫",
    "pinyin": "qíngfū"
  },
  {
    "hanzi": "情郎",
    "pinyin": "qíngláng"
  },
  {
    "hanzi": "一家言",
    "pinyin": "yījiāyán"
  },
  {
    "hanzi": "求贤若渴",
    "pinyin": "qiúxiánruòkě"
  },
  {
    "hanzi": "曲径通幽",
    "pinyin": "qūjìngtōngyōu"
  },
  {
    "hanzi": "雪雕",
    "pinyin": "xuědiāo"
  },
  {
    "hanzi": "僧徒",
    "pinyin": "sēngtú"
  },
  {
    "hanzi": "沙丁鱼",
    "pinyin": "shādīngyú"
  },
  {
    "hanzi": "伤悲",
    "pinyin": "shāngbēi"
  },
  {
    "hanzi": "伤神",
    "pinyin": "shāngshén"
  },
  {
    "hanzi": "身架",
    "pinyin": "shēnjià"
  },
  {
    "hanzi": "神怪",
    "pinyin": "shénguài"
  },
  {
    "hanzi": "接龙",
    "pinyin": "jiēlóng"
  },
  {
    "hanzi": "生冷",
    "pinyin": "shēnglěng"
  },
  {
    "hanzi": "逆天",
    "pinyin": "nìtiān"
  },
  {
    "hanzi": "声名狼藉",
    "pinyin": "shēngmínglángjí"
  },
  {
    "hanzi": "声腔",
    "pinyin": "shēngqiāng"
  },
  {
    "hanzi": "笙歌",
    "pinyin": "shēnggē"
  },
  {
    "hanzi": "石臼",
    "pinyin": "shíjiù"
  },
  {
    "hanzi": "实职",
    "pinyin": "shízhí"
  },
  {
    "hanzi": "拾取",
    "pinyin": "shíqǔ"
  },
  {
    "hanzi": "史话",
    "pinyin": "shǐhuà"
  },
  {
    "hanzi": "示爱",
    "pinyin": "shì'ài"
  },
  {
    "hanzi": "事功",
    "pinyin": "shìgōng"
  },
  {
    "hanzi": "熟路",
    "pinyin": "shúlù"
  },
  {
    "hanzi": "打闷棍",
    "pinyin": "dǎmèngùn"
  },
  {
    "hanzi": "属相",
    "pinyin": "shǔxiang"
  },
  {
    "hanzi": "闪躲",
    "pinyin": "shǎnduǒ"
  },
  {
    "hanzi": "顺手牵羊",
    "pinyin": "shùnshǒuqiānyáng"
  },
  {
    "hanzi": "燧石",
    "pinyin": "suìshí"
  },
  {
    "hanzi": "索还",
    "pinyin": "suǒhuán"
  },
  {
    "hanzi": "台基",
    "pinyin": "táijī"
  },
  {
    "hanzi": "太空船",
    "pinyin": "tàikōngchuán"
  },
  {
    "hanzi": "谈锋",
    "pinyin": "tánfēng"
  },
  {
    "hanzi": "坦白从宽",
    "pinyin": "tǎnbáicóngkuān"
  },
  {
    "hanzi": "绦虫",
    "pinyin": "tāochóng"
  },
  {
    "hanzi": "套套",
    "pinyin": "tàotao"
  },
  {
    "hanzi": "调节税",
    "pinyin": "tiáojiéshuì"
  },
  {
    "hanzi": "猎艳",
    "pinyin": "lièyàn"
  },
  {
    "hanzi": "挑拨离间",
    "pinyin": "tiǎobōlíjiàn"
  },
  {
    "hanzi": "听其自然",
    "pinyin": "tīngqízìrán"
  },
  {
    "hanzi": "停航",
    "pinyin": "tíngháng"
  },
  {
    "hanzi": "偷越",
    "pinyin": "tōuyuè"
  },
  {
    "hanzi": "投拍",
    "pinyin": "tóupāi"
  },
  {
    "hanzi": "吞云吐雾",
    "pinyin": "tūnyúntǔwù"
  },
  {
    "hanzi": "外借",
    "pinyin": "wàijiè"
  },
  {
    "hanzi": "晚育",
    "pinyin": "wǎnyù"
  },
  {
    "hanzi": "温煦",
    "pinyin": "wēnxù"
  },
  {
    "hanzi": "稀有金属",
    "pinyin": "xīyǒujīnshǔ"
  },
  {
    "hanzi": "溪涧",
    "pinyin": "xījiàn"
  },
  {
    "hanzi": "洗煤",
    "pinyin": "xǐméi"
  },
  {
    "hanzi": "上照",
    "pinyin": "shàngzhào"
  },
  {
    "hanzi": "喜乐",
    "pinyin": "xǐlè"
  },
  {
    "hanzi": "脸厚",
    "pinyin": "liǎnhòu"
  },
  {
    "hanzi": "喜信",
    "pinyin": "xǐxìn"
  },
  {
    "hanzi": "闲逸",
    "pinyin": "xiányì"
  },
  {
    "hanzi": "贤臣",
    "pinyin": "xiánchén"
  },
  {
    "hanzi": "弦歌",
    "pinyin": "xiángē"
  },
  {
    "hanzi": "向隅",
    "pinyin": "xiàngyú"
  },
  {
    "hanzi": "小户人家",
    "pinyin": "xiǎohùrénjiā"
  },
  {
    "hanzi": "小账",
    "pinyin": "xiǎozhàng"
  },
  {
    "hanzi": "小卒",
    "pinyin": "xiǎozú"
  },
  {
    "hanzi": "斜线",
    "pinyin": "xiéxiàn"
  },
  {
    "hanzi": "薪资",
    "pinyin": "xīnzī"
  },
  {
    "hanzi": "信史",
    "pinyin": "xìnshǐ"
  },
  {
    "hanzi": "星团",
    "pinyin": "xīngtuán"
  },
  {
    "hanzi": "行李卷儿",
    "pinyin": "xínglijuǎnr"
  },
  {
    "hanzi": "行商",
    "pinyin": "xíngshāng"
  },
  {
    "hanzi": "杏黄",
    "pinyin": "xìnghuáng"
  },
  {
    "hanzi": "胸片",
    "pinyin": "xiōngpiàn"
  },
  {
    "hanzi": "虚情假意",
    "pinyin": "xūqíngjiǎyì"
  },
  {
    "hanzi": "雪梨",
    "pinyin": "xuělí"
  },
  {
    "hanzi": "血友病",
    "pinyin": "xuèyǒubìng"
  },
  {
    "hanzi": "扬旗",
    "pinyin": "yángqí"
  },
  {
    "hanzi": "扬琴",
    "pinyin": "yángqín"
  },
  {
    "hanzi": "羊水",
    "pinyin": "yángshuǐ"
  },
  {
    "hanzi": "腰刀",
    "pinyin": "yāodāo"
  },
  {
    "hanzi": "耀目",
    "pinyin": "yàomù"
  },
  {
    "hanzi": "一扫而空",
    "pinyin": "yīsǎo'érkōng"
  },
  {
    "hanzi": "倚赖",
    "pinyin": "yǐlài"
  },
  {
    "hanzi": "印花布",
    "pinyin": "yìnhuābù"
  },
  {
    "hanzi": "佣工",
    "pinyin": "yōnggōng"
  },
  {
    "hanzi": "勇悍",
    "pinyin": "yǒnghàn"
  },
  {
    "hanzi": "游侠",
    "pinyin": "yóuxiá"
  },
  {
    "hanzi": "瑜伽",
    "pinyin": "yújiā"
  },
  {
    "hanzi": "殒命",
    "pinyin": "yǔnmìng"
  },
  {
    "hanzi": "运笔",
    "pinyin": "yùnbǐ"
  },
  {
    "hanzi": "贼胆",
    "pinyin": "zéidǎn"
  },
  {
    "hanzi": "站柜台",
    "pinyin": "zhànguìtái"
  },
  {
    "hanzi": "征候",
    "pinyin": "zhēnghòu"
  },
  {
    "hanzi": "脏钱",
    "pinyin": "zāngqián"
  },
  {
    "hanzi": "正极",
    "pinyin": "zhèngjí"
  },
  {
    "hanzi": "指靠",
    "pinyin": "zhǐkào"
  },
  {
    "hanzi": "舟车",
    "pinyin": "zhōuchē"
  },
  {
    "hanzi": "洲际导弹",
    "pinyin": "zhōujìdǎodàn"
  },
  {
    "hanzi": "专科生",
    "pinyin": "zhuānkēshēng"
  },
  {
    "hanzi": "转运站",
    "pinyin": "zhuǎnyùnzhàn"
  },
  {
    "hanzi": "自忖",
    "pinyin": "zìcǔn"
  },
  {
    "hanzi": "自许",
    "pinyin": "zìxǔ"
  },
  {
    "hanzi": "走钢丝",
    "pinyin": "zǒugāngsī"
  },
  {
    "hanzi": "作乐",
    "pinyin": "zuòyuè"
  },
  {
    "hanzi": "摆列",
    "pinyin": "bǎiliè"
  },
  {
    "hanzi": "绑扎",
    "pinyin": "bǎngzā"
  },
  {
    "hanzi": "棒子面",
    "pinyin": "bàngzimiàn"
  },
  {
    "hanzi": "报修",
    "pinyin": "bàoxiū"
  },
  {
    "hanzi": "卑污",
    "pinyin": "bēiwū"
  },
  {
    "hanzi": "被套",
    "pinyin": "bèitào"
  },
  {
    "hanzi": "迸射",
    "pinyin": "bèngshè"
  },
  {
    "hanzi": "边门",
    "pinyin": "biānmén"
  },
  {
    "hanzi": "编舞",
    "pinyin": "biānwǔ"
  },
  {
    "hanzi": "扁圆",
    "pinyin": "biǎnyuán"
  },
  {
    "hanzi": "表亲",
    "pinyin": "biǎoqīn"
  },
  {
    "hanzi": "冰糖葫芦",
    "pinyin": "bīngtánghúlu"
  },
  {
    "hanzi": "跛脚",
    "pinyin": "bǒjiǎo"
  },
  {
    "hanzi": "参禅",
    "pinyin": "cānchán"
  },
  {
    "hanzi": "苍松",
    "pinyin": "cāngsōng"
  },
  {
    "hanzi": "藏污纳垢",
    "pinyin": "cángwūnàgòu"
  },
  {
    "hanzi": "草野",
    "pinyin": "cǎoyě"
  },
  {
    "hanzi": "产儿",
    "pinyin": "chǎn'ér"
  },
  {
    "hanzi": "产婆",
    "pinyin": "chǎnpó"
  },
  {
    "hanzi": "抄近儿",
    "pinyin": "chāojìnr"
  },
  {
    "hanzi": "车把式",
    "pinyin": "chēbǎshi"
  },
  {
    "hanzi": "车况",
    "pinyin": "chēkuàng"
  },
  {
    "hanzi": "车前子",
    "pinyin": "chēqiánzǐ"
  },
  {
    "hanzi": "彻悟",
    "pinyin": "chèwù"
  },
  {
    "hanzi": "陈请",
    "pinyin": "chénqǐng"
  },
  {
    "hanzi": "呈祥",
    "pinyin": "chéngxiáng"
  },
  {
    "hanzi": "秤杆",
    "pinyin": "chènggǎn"
  },
  {
    "hanzi": "持械",
    "pinyin": "chíxiè"
  },
  {
    "hanzi": "虫蛀",
    "pinyin": "chóngzhù"
  },
  {
    "hanzi": "出洋相",
    "pinyin": "chūyángxiàng"
  },
  {
    "hanzi": "初小",
    "pinyin": "chūxiǎo"
  },
  {
    "hanzi": "串珠",
    "pinyin": "chuànzhū"
  },
  {
    "hanzi": "此致",
    "pinyin": "cǐzhì"
  },
  {
    "hanzi": "打滑",
    "pinyin": "dǎhuá"
  },
  {
    "hanzi": "大腹便便",
    "pinyin": "dàfùpiánpián"
  },
  {
    "hanzi": "大实话",
    "pinyin": "dàshíhuà"
  },
  {
    "hanzi": "叨咕",
    "pinyin": "dáogu"
  },
  {
    "hanzi": "盗墓",
    "pinyin": "dàomù"
  },
  {
    "hanzi": "地方税",
    "pinyin": "dìfāngshuì"
  },
  {
    "hanzi": "电声",
    "pinyin": "diànshēng"
  },
  {
    "hanzi": "冬虫夏草",
    "pinyin": "dōngchóngxiàcǎo"
  },
  {
    "hanzi": "独门",
    "pinyin": "dúmén"
  },
  {
    "hanzi": "断路",
    "pinyin": "duànlù"
  },
  {
    "hanzi": "翻供",
    "pinyin": "fāngòng"
  },
  {
    "hanzi": "飞沙走石",
    "pinyin": "fēishāzǒushí"
  },
  {
    "hanzi": "挂拍",
    "pinyin": "guàpāi"
  },
  {
    "hanzi": "风景点",
    "pinyin": "fēngjǐngdiǎn"
  },
  {
    "hanzi": "辐射能",
    "pinyin": "fúshènéng"
  },
  {
    "hanzi": "附上",
    "pinyin": "fùshàng"
  },
  {
    "hanzi": "副手",
    "pinyin": "fùshǒu"
  },
  {
    "hanzi": "高粱米",
    "pinyin": "gāoliángmǐ"
  },
  {
    "hanzi": "高山仰止",
    "pinyin": "gāoshānyǎngzhǐ"
  },
  {
    "hanzi": "高士",
    "pinyin": "gāoshì"
  },
  {
    "hanzi": "告病",
    "pinyin": "gàobìng"
  },
  {
    "hanzi": "嗝儿",
    "pinyin": "gér"
  },
  {
    "hanzi": "工作餐",
    "pinyin": "gōngzuòcān"
  },
  {
    "hanzi": "恭谨",
    "pinyin": "gōngjǐn"
  },
  {
    "hanzi": "骨盆",
    "pinyin": "gǔpén"
  },
  {
    "hanzi": "鼓槌",
    "pinyin": "gǔchuí"
  },
  {
    "hanzi": "挂齿",
    "pinyin": "guàchǐ"
  },
  {
    "hanzi": "关张",
    "pinyin": "guānzhāng"
  },
  {
    "hanzi": "观览",
    "pinyin": "guānlǎn"
  },
  {
    "hanzi": "管饭",
    "pinyin": "guǎnfàn"
  },
  {
    "hanzi": "哈腰",
    "pinyin": "hāyāo"
  },
  {
    "hanzi": "喊冤",
    "pinyin": "hǎnyuān"
  },
  {
    "hanzi": "呵叱",
    "pinyin": "hēchì"
  },
  {
    "hanzi": "合子",
    "pinyin": "hézi"
  },
  {
    "hanzi": "和数",
    "pinyin": "héshù"
  },
  {
    "hanzi": "核电厂",
    "pinyin": "hédiànchǎng"
  },
  {
    "hanzi": "盒带",
    "pinyin": "hédài"
  },
  {
    "hanzi": "后发制人",
    "pinyin": "hòufāzhìrén"
  },
  {
    "hanzi": "后手",
    "pinyin": "hòushǒu"
  },
  {
    "hanzi": "狐朋狗友",
    "pinyin": "húpénggǒuyǒu"
  },
  {
    "hanzi": "滑竿",
    "pinyin": "huágān"
  },
  {
    "hanzi": "环海",
    "pinyin": "huánhǎi"
  },
  {
    "hanzi": "缓兵之计",
    "pinyin": "huǎnbīngzhījì"
  },
  {
    "hanzi": "黄雀",
    "pinyin": "huángquè"
  },
  {
    "hanzi": "昏头昏脑",
    "pinyin": "hūntóuhūnnǎo"
  },
  {
    "hanzi": "混事",
    "pinyin": "hùnshì"
  },
  {
    "hanzi": "火烧眉毛",
    "pinyin": "huǒshāoméimao"
  },
  {
    "hanzi": "机械手",
    "pinyin": "jīxièshǒu"
  },
  {
    "hanzi": "疾恶如仇",
    "pinyin": "jí'èrúchóu"
  },
  {
    "hanzi": "蒺藜",
    "pinyin": "jílí"
  },
  {
    "hanzi": "家蚕",
    "pinyin": "jiācán"
  },
  {
    "hanzi": "将错就错",
    "pinyin": "jiāngcuòjiùcuò"
  },
  {
    "hanzi": "茭白",
    "pinyin": "jiāobái"
  },
  {
    "hanzi": "绞死",
    "pinyin": "jiǎosǐ"
  },
  {
    "hanzi": "缴付",
    "pinyin": "jiǎofù"
  },
  {
    "hanzi": "看医生",
    "pinyin": "kànyīshēng"
  },
  {
    "hanzi": "胯骨",
    "pinyin": "kuàgǔ"
  },
  {
    "hanzi": "老相识",
    "pinyin": "lǎoxiāngshí"
  },
  {
    "hanzi": "类固醇",
    "pinyin": "lèigùchún"
  },
  {
    "hanzi": "凉意",
    "pinyin": "liángyì"
  },
  {
    "hanzi": "林涛",
    "pinyin": "líntāo"
  },
  {
    "hanzi": "鹿茸",
    "pinyin": "lùróng"
  },
  {
    "hanzi": "漫溢",
    "pinyin": "mànyì"
  },
  {
    "hanzi": "毛裤",
    "pinyin": "máokù"
  },
  {
    "hanzi": "房补",
    "pinyin": "fángbǔ"
  },
  {
    "hanzi": "帽徽",
    "pinyin": "màohuī"
  },
  {
    "hanzi": "煤耗",
    "pinyin": "méihào"
  },
  {
    "hanzi": "妙策",
    "pinyin": "miàocè"
  },
  {
    "hanzi": "明达",
    "pinyin": "míngdá"
  },
  {
    "hanzi": "抹灰",
    "pinyin": "mǒhuī"
  },
  {
    "hanzi": "沫子",
    "pinyin": "mòzi"
  },
  {
    "hanzi": "目光短浅",
    "pinyin": "mùguāngduǎnqiǎn"
  },
  {
    "hanzi": "脑汁",
    "pinyin": "nǎozhī"
  },
  {
    "hanzi": "内服",
    "pinyin": "nèifú"
  },
  {
    "hanzi": "能言善辩",
    "pinyin": "néngyánshànbiàn"
  },
  {
    "hanzi": "孽种",
    "pinyin": "nièzhǒng"
  },
  {
    "hanzi": "呕血",
    "pinyin": "ǒuxuè"
  },
  {
    "hanzi": "盘坐",
    "pinyin": "pánzuò"
  },
  {
    "hanzi": "配比",
    "pinyin": "pèibǐ"
  },
  {
    "hanzi": "屁滚尿流",
    "pinyin": "pìgǔnniàoliú"
  },
  {
    "hanzi": "僻远",
    "pinyin": "pìyuǎn"
  },
  {
    "hanzi": "骈体",
    "pinyin": "piántǐ"
  },
  {
    "hanzi": "破镜重圆",
    "pinyin": "pòjìngchóngyuán"
  },
  {
    "hanzi": "汽灯",
    "pinyin": "qìdēng"
  },
  {
    "hanzi": "巧言",
    "pinyin": "qiǎoyán"
  },
  {
    "hanzi": "倾巢",
    "pinyin": "qīngcháo"
  },
  {
    "hanzi": "穷兵黩武",
    "pinyin": "qióngbīngdúwǔ"
  },
  {
    "hanzi": "求雨",
    "pinyin": "qiúyǔ"
  },
  {
    "hanzi": "去皮",
    "pinyin": "qùpí"
  },
  {
    "hanzi": "犬马",
    "pinyin": "quǎnmǎ"
  },
  {
    "hanzi": "人地生疏",
    "pinyin": "réndìshēngshū"
  },
  {
    "hanzi": "人心不古",
    "pinyin": "rénxīnbùgǔ"
  },
  {
    "hanzi": "人妖",
    "pinyin": "rényāo"
  },
  {
    "hanzi": "容身",
    "pinyin": "róngshēn"
  },
  {
    "hanzi": "溶血",
    "pinyin": "róngxuè"
  },
  {
    "hanzi": "入定",
    "pinyin": "rùdìng"
  },
  {
    "hanzi": "撒播",
    "pinyin": "sǎbō"
  },
  {
    "hanzi": "建账",
    "pinyin": "jiànzhàng"
  },
  {
    "hanzi": "桑葚",
    "pinyin": "sāngshèn"
  },
  {
    "hanzi": "瘙痒",
    "pinyin": "sàoyǎng"
  },
  {
    "hanzi": "摄影棚",
    "pinyin": "shèyǐngpéng"
  },
  {
    "hanzi": "绳套",
    "pinyin": "shéngtào"
  },
  {
    "hanzi": "失计",
    "pinyin": "shījì"
  },
  {
    "hanzi": "什锦",
    "pinyin": "shíjǐn"
  },
  {
    "hanzi": "拾遗补缺",
    "pinyin": "shíyíbǔquē"
  },
  {
    "hanzi": "世仇",
    "pinyin": "shìchóu"
  },
  {
    "hanzi": "事到临头",
    "pinyin": "shìdàolíntóu"
  },
  {
    "hanzi": "收殓",
    "pinyin": "shōuliàn"
  },
  {
    "hanzi": "受业",
    "pinyin": "shòuyè"
  },
  {
    "hanzi": "耍笑",
    "pinyin": "shuǎxiào"
  },
  {
    "hanzi": "霜期",
    "pinyin": "shuāngqī"
  },
  {
    "hanzi": "睡袍",
    "pinyin": "shuìpáo"
  },
  {
    "hanzi": "撕打",
    "pinyin": "sīdǎ"
  },
  {
    "hanzi": "四海为家",
    "pinyin": "sìhǎiwéijiā"
  },
  {
    "hanzi": "汤水",
    "pinyin": "tāngshuǐ"
  },
  {
    "hanzi": "特首",
    "pinyin": "tèshǒu"
  },
  {
    "hanzi": "通栏",
    "pinyin": "tōnglán"
  },
  {
    "hanzi": "头雁",
    "pinyin": "tóuyàn"
  },
  {
    "hanzi": "投合",
    "pinyin": "tóuhé"
  },
  {
    "hanzi": "托病",
    "pinyin": "tuōbìng"
  },
  {
    "hanzi": "脱发",
    "pinyin": "tuōfà"
  },
  {
    "hanzi": "脱色",
    "pinyin": "tuōsè"
  },
  {
    "hanzi": "驼峰",
    "pinyin": "tuófēng"
  },
  {
    "hanzi": "外孙子",
    "pinyin": "wàisūnzi"
  },
  {
    "hanzi": "外溢",
    "pinyin": "wàiyì"
  },
  {
    "hanzi": "外引",
    "pinyin": "wàiyǐn"
  },
  {
    "hanzi": "万福",
    "pinyin": "wànfú"
  },
  {
    "hanzi": "万贯",
    "pinyin": "wànguàn"
  },
  {
    "hanzi": "望月",
    "pinyin": "wàngyuè"
  },
  {
    "hanzi": "围腰",
    "pinyin": "wéiyāo"
  },
  {
    "hanzi": "味同嚼蜡",
    "pinyin": "wèitóngjiáolà"
  },
  {
    "hanzi": "蔚为壮观",
    "pinyin": "wèiwéizhuàngguān"
  },
  {
    "hanzi": "蜗居",
    "pinyin": "wōjū"
  },
  {
    "hanzi": "乌七八糟",
    "pinyin": "wūqībāzāo"
  },
  {
    "hanzi": "污渍",
    "pinyin": "wūzì"
  },
  {
    "hanzi": "无为而治",
    "pinyin": "wúwéi'érzhì"
  },
  {
    "hanzi": "五爱",
    "pinyin": "wǔ'ài"
  },
  {
    "hanzi": "造地",
    "pinyin": "zàodì"
  },
  {
    "hanzi": "五线谱",
    "pinyin": "wǔxiànpǔ"
  },
  {
    "hanzi": "晤面",
    "pinyin": "wùmiàn"
  },
  {
    "hanzi": "雾里看花",
    "pinyin": "wùlǐkànhuā"
  },
  {
    "hanzi": "喜怒无常",
    "pinyin": "xǐnùwúcháng"
  },
  {
    "hanzi": "系铃人",
    "pinyin": "xìlíngrén"
  },
  {
    "hanzi": "先睹为快",
    "pinyin": "xiāndǔwéikuài"
  },
  {
    "hanzi": "贤能",
    "pinyin": "xiánnéng"
  },
  {
    "hanzi": "小过",
    "pinyin": "xiǎoguò"
  },
  {
    "hanzi": "心肌梗死",
    "pinyin": "xīnjīgěngsǐ"
  },
  {
    "hanzi": "幸会",
    "pinyin": "xìnghuì"
  },
  {
    "hanzi": "凶横",
    "pinyin": "xiōnghèng"
  },
  {
    "hanzi": "虚岁",
    "pinyin": "xūsuì"
  },
  {
    "hanzi": "血雨腥风",
    "pinyin": "xuèyǔxīngfēng"
  },
  {
    "hanzi": "压顶",
    "pinyin": "yādǐng"
  },
  {
    "hanzi": "字母词",
    "pinyin": "zìmǔcí"
  },
  {
    "hanzi": "压路机",
    "pinyin": "yālùjī"
  },
  {
    "hanzi": "烟具",
    "pinyin": "yānjù"
  },
  {
    "hanzi": "盐巴",
    "pinyin": "yánbā"
  },
  {
    "hanzi": "眼角膜",
    "pinyin": "yǎnjiǎomó"
  },
  {
    "hanzi": "洋化",
    "pinyin": "yánghuà"
  },
  {
    "hanzi": "徭役",
    "pinyin": "yáoyì"
  },
  {
    "hanzi": "一马平川",
    "pinyin": "yīmǎpíngchuān"
  },
  {
    "hanzi": "意气用事",
    "pinyin": "yìqìyòngshì"
  },
  {
    "hanzi": "臆测",
    "pinyin": "yìcè"
  },
  {
    "hanzi": "隐衷",
    "pinyin": "yǐnzhōng"
  },
  {
    "hanzi": "影视圈",
    "pinyin": "yǐngshìquān"
  },
  {
    "hanzi": "庸医",
    "pinyin": "yōngyī"
  },
  {
    "hanzi": "淤血",
    "pinyin": "yūxuè"
  },
  {
    "hanzi": "鱼油",
    "pinyin": "yúyóu"
  },
  {
    "hanzi": "渔猎",
    "pinyin": "yúliè"
  },
  {
    "hanzi": "愚见",
    "pinyin": "yújiàn"
  },
  {
    "hanzi": "原地踏步",
    "pinyin": "yuándìtàbù"
  },
  {
    "hanzi": "远视",
    "pinyin": "yuǎnshì"
  },
  {
    "hanzi": "运动衣",
    "pinyin": "yùndòngyī"
  },
  {
    "hanzi": "杂陈",
    "pinyin": "záchén"
  },
  {
    "hanzi": "皂角",
    "pinyin": "zàojiǎo"
  },
  {
    "hanzi": "诈降",
    "pinyin": "zhàxiáng"
  },
  {
    "hanzi": "枝蔓",
    "pinyin": "zhīmàn"
  },
  {
    "hanzi": "治服",
    "pinyin": "zhìfú"
  },
  {
    "hanzi": "周转金",
    "pinyin": "zhōuzhuǎnjīn"
  },
  {
    "hanzi": "啁啾",
    "pinyin": "zhōujiū"
  },
  {
    "hanzi": "助纣为虐",
    "pinyin": "zhùzhòuwéinüè"
  },
  {
    "hanzi": "装神弄鬼",
    "pinyin": "zhuāngshénnòngguǐ"
  },
  {
    "hanzi": "追怀",
    "pinyin": "zhuīhuái"
  },
  {
    "hanzi": "追尾",
    "pinyin": "zhuīwěi"
  },
  {
    "hanzi": "自成一家",
    "pinyin": "zìchéngyījiā"
  },
  {
    "hanzi": "身教",
    "pinyin": "shēnjiào"
  },
  {
    "hanzi": "阿司匹林",
    "pinyin": "āsīpǐlín"
  },
  {
    "hanzi": "白肉",
    "pinyin": "báiròu"
  },
  {
    "hanzi": "白事",
    "pinyin": "báishì"
  },
  {
    "hanzi": "白血球",
    "pinyin": "báixuèqiú"
  },
  {
    "hanzi": "摆阔",
    "pinyin": "bǎikuò"
  },
  {
    "hanzi": "拜辞",
    "pinyin": "bàicí"
  },
  {
    "hanzi": "板床",
    "pinyin": "bǎnchuáng"
  },
  {
    "hanzi": "半腰",
    "pinyin": "bànyāo"
  },
  {
    "hanzi": "报春花",
    "pinyin": "bàochūnhuā"
  },
  {
    "hanzi": "暴死",
    "pinyin": "bàosǐ"
  },
  {
    "hanzi": "爆炒",
    "pinyin": "bàochǎo"
  },
  {
    "hanzi": "悲号",
    "pinyin": "bēiháo"
  },
  {
    "hanzi": "背人",
    "pinyin": "bèirén"
  },
  {
    "hanzi": "本埠",
    "pinyin": "běnbù"
  },
  {
    "hanzi": "变价",
    "pinyin": "biànjià"
  },
  {
    "hanzi": "兵械",
    "pinyin": "bīngxiè"
  },
  {
    "hanzi": "波束",
    "pinyin": "bōshù"
  },
  {
    "hanzi": "草民",
    "pinyin": "cǎomín"
  },
  {
    "hanzi": "拆穿",
    "pinyin": "chāichuān"
  },
  {
    "hanzi": "长逝",
    "pinyin": "chángshì"
  },
  {
    "hanzi": "唱高调",
    "pinyin": "chànggāodiào"
  },
  {
    "hanzi": "成名作",
    "pinyin": "chéngmíngzuò"
  },
  {
    "hanzi": "成人之美",
    "pinyin": "chéngrénzhīměi"
  },
  {
    "hanzi": "成文法",
    "pinyin": "chéngwénfǎ"
  },
  {
    "hanzi": "呈交",
    "pinyin": "chéngjiāo"
  },
  {
    "hanzi": "城垛",
    "pinyin": "chéngduǒ"
  },
  {
    "hanzi": "逞凶",
    "pinyin": "chěngxiōng"
  },
  {
    "hanzi": "吃不准",
    "pinyin": "chībuzhǔn"
  },
  {
    "hanzi": "吃老本",
    "pinyin": "chīlǎoběn"
  },
  {
    "hanzi": "垂死挣扎",
    "pinyin": "chuísǐzhēngzhá"
  },
  {
    "hanzi": "从戎",
    "pinyin": "cóngróng"
  },
  {
    "hanzi": "粗通",
    "pinyin": "cūtōng"
  },
  {
    "hanzi": "寸断",
    "pinyin": "cùnduàn"
  },
  {
    "hanzi": "寸土",
    "pinyin": "cùntǔ"
  },
  {
    "hanzi": "大集体",
    "pinyin": "dàjítǐ"
  },
  {
    "hanzi": "大前天",
    "pinyin": "dàqiántiān"
  },
  {
    "hanzi": "单用",
    "pinyin": "dānyòng"
  },
  {
    "hanzi": "弹丸之地",
    "pinyin": "dànwánzhīdì"
  },
  {
    "hanzi": "倒运",
    "pinyin": "dǎoyùn"
  },
  {
    "hanzi": "颠倒是非",
    "pinyin": "diāndǎoshìfēi"
  },
  {
    "hanzi": "电汇",
    "pinyin": "diànhuì"
  },
  {
    "hanzi": "斗拱",
    "pinyin": "dǒugǒng"
  },
  {
    "hanzi": "短讯",
    "pinyin": "duǎnxùn"
  },
  {
    "hanzi": "堆肥",
    "pinyin": "duīféi"
  },
  {
    "hanzi": "发报",
    "pinyin": "fābào"
  },
  {
    "hanzi": "发绿",
    "pinyin": "fālǜ"
  },
  {
    "hanzi": "反绑",
    "pinyin": "fǎnbǎng"
  },
  {
    "hanzi": "反扒",
    "pinyin": "fǎnpá"
  },
  {
    "hanzi": "反诉",
    "pinyin": "fǎnsù"
  },
  {
    "hanzi": "防暴警察",
    "pinyin": "fángbàojǐngchá"
  },
  {
    "hanzi": "防寒服",
    "pinyin": "fánghánfú"
  },
  {
    "hanzi": "飞扬跋扈",
    "pinyin": "fēiyángbáhù"
  },
  {
    "hanzi": "粪车",
    "pinyin": "fènchē"
  },
  {
    "hanzi": "风声鹤唳",
    "pinyin": "fēngshēnghèlì"
  },
  {
    "hanzi": "氟利昂",
    "pinyin": "fúlì'áng"
  },
  {
    "hanzi": "俯拾即是",
    "pinyin": "fǔshíjíshì"
  },
  {
    "hanzi": "概略",
    "pinyin": "gàilüè"
  },
  {
    "hanzi": "敢是",
    "pinyin": "gǎnshì"
  },
  {
    "hanzi": "刚正",
    "pinyin": "gāngzhèng"
  },
  {
    "hanzi": "工笔画",
    "pinyin": "gōngbǐhuà"
  },
  {
    "hanzi": "工于",
    "pinyin": "gōngyú"
  },
  {
    "hanzi": "公举",
    "pinyin": "gōngjǔ"
  },
  {
    "hanzi": "勾魂",
    "pinyin": "gōuhún"
  },
  {
    "hanzi": "狗崽子",
    "pinyin": "gǒuzǎizi"
  },
  {
    "hanzi": "鼓风机",
    "pinyin": "gǔfēngjī"
  },
  {
    "hanzi": "刮痧",
    "pinyin": "guāshā"
  },
  {
    "hanzi": "寡居",
    "pinyin": "guǎjū"
  },
  {
    "hanzi": "挂冠",
    "pinyin": "guàguān"
  },
  {
    "hanzi": "光火",
    "pinyin": "guānghuǒ"
  },
  {
    "hanzi": "归程",
    "pinyin": "guīchéng"
  },
  {
    "hanzi": "归化",
    "pinyin": "guīhuà"
  },
  {
    "hanzi": "鬼哭狼嚎",
    "pinyin": "guǐkūlángháo"
  },
  {
    "hanzi": "鬼头鬼脑",
    "pinyin": "guǐtóuguǐnǎo"
  },
  {
    "hanzi": "滚瓜烂熟",
    "pinyin": "gǔnguālànshú"
  },
  {
    "hanzi": "果腹",
    "pinyin": "guǒfù"
  },
  {
    "hanzi": "酣战",
    "pinyin": "hānzhàn"
  },
  {
    "hanzi": "皓齿",
    "pinyin": "hàochǐ"
  },
  {
    "hanzi": "荷载",
    "pinyin": "hèzài"
  },
  {
    "hanzi": "黑色幽默",
    "pinyin": "hēisèyōumò"
  },
  {
    "hanzi": "横断面",
    "pinyin": "héngduànmiàn"
  },
  {
    "hanzi": "宏论",
    "pinyin": "hónglùn"
  },
  {
    "hanzi": "厚意",
    "pinyin": "hòuyì"
  },
  {
    "hanzi": "胡椒面儿",
    "pinyin": "hújiāomiànr"
  },
  {
    "hanzi": "花腔",
    "pinyin": "huāqiāng"
  },
  {
    "hanzi": "还账",
    "pinyin": "huánzhàng"
  },
  {
    "hanzi": "黄道吉日",
    "pinyin": "huángdàojírì"
  },
  {
    "hanzi": "毁谤",
    "pinyin": "huǐbàng"
  },
  {
    "hanzi": "婚俗",
    "pinyin": "hūnsú"
  },
  {
    "hanzi": "纪纲",
    "pinyin": "jìgāng"
  },
  {
    "hanzi": "家鸽",
    "pinyin": "jiāgē"
  },
  {
    "hanzi": "拣选",
    "pinyin": "jiǎnxuǎn"
  },
  {
    "hanzi": "贱人",
    "pinyin": "jiànrén"
  },
  {
    "hanzi": "姜汤",
    "pinyin": "jiāngtāng"
  },
  {
    "hanzi": "结婚照",
    "pinyin": "jiéhūnzhào"
  },
  {
    "hanzi": "金针",
    "pinyin": "jīnzhēn"
  },
  {
    "hanzi": "进款",
    "pinyin": "jìnkuǎn"
  },
  {
    "hanzi": "禁食",
    "pinyin": "jìnshí"
  },
  {
    "hanzi": "警徽",
    "pinyin": "jǐnghuī"
  },
  {
    "hanzi": "竞拍",
    "pinyin": "jìngpāi"
  },
  {
    "hanzi": "救险",
    "pinyin": "jiùxiǎn"
  },
  {
    "hanzi": "开裆裤",
    "pinyin": "kāidāngkù"
  },
  {
    "hanzi": "苛捐杂税",
    "pinyin": "kējuānzáshuì"
  },
  {
    "hanzi": "空喊",
    "pinyin": "kōnghǎn"
  },
  {
    "hanzi": "空架子",
    "pinyin": "kōngjiàzi"
  },
  {
    "hanzi": "口诛笔伐",
    "pinyin": "kǒuzhūbǐfá"
  },
  {
    "hanzi": "苦差",
    "pinyin": "kǔchāi"
  },
  {
    "hanzi": "髋关节",
    "pinyin": "kuānguānjié"
  },
  {
    "hanzi": "来潮",
    "pinyin": "láicháo"
  },
  {
    "hanzi": "劳改犯",
    "pinyin": "láogǎifàn"
  },
  {
    "hanzi": "老旦",
    "pinyin": "lǎodàn"
  },
  {
    "hanzi": "冷板凳",
    "pinyin": "lěngbǎndèng"
  },
  {
    "hanzi": "两可",
    "pinyin": "liǎngkě"
  },
  {
    "hanzi": "两全",
    "pinyin": "liǎngquán"
  },
  {
    "hanzi": "伶牙俐齿",
    "pinyin": "língyálìchǐ"
  },
  {
    "hanzi": "罗曼蒂克",
    "pinyin": "luómàndìkè"
  },
  {
    "hanzi": "落魄",
    "pinyin": "luòpò"
  },
  {
    "hanzi": "马赛克",
    "pinyin": "mǎsàikè"
  },
  {
    "hanzi": "漫卷",
    "pinyin": "mànjuǎn"
  },
  {
    "hanzi": "没着落",
    "pinyin": "méizhuóluò"
  },
  {
    "hanzi": "明春",
    "pinyin": "míngchūn"
  },
  {
    "hanzi": "木偶戏",
    "pinyin": "mù'ǒuxì"
  },
  {
    "hanzi": "耙子",
    "pinyin": "pázi"
  },
  {
    "hanzi": "旁门",
    "pinyin": "pángmén"
  },
  {
    "hanzi": "皮包公司",
    "pinyin": "píbāogōngsī"
  },
  {
    "hanzi": "翩跹",
    "pinyin": "piānxiān"
  },
  {
    "hanzi": "片剂",
    "pinyin": "piànjì"
  },
  {
    "hanzi": "飘移",
    "pinyin": "piāoyí"
  },
  {
    "hanzi": "瓢虫",
    "pinyin": "piáochóng"
  },
  {
    "hanzi": "瓢泼大雨",
    "pinyin": "piáopōdàyǔ"
  },
  {
    "hanzi": "瓶塞",
    "pinyin": "píngsāi"
  },
  {
    "hanzi": "妻弟",
    "pinyin": "qīdì"
  },
  {
    "hanzi": "欺瞒",
    "pinyin": "qīmán"
  },
  {
    "hanzi": "漆画",
    "pinyin": "qīhuà"
  },
  {
    "hanzi": "奇趣",
    "pinyin": "qíqù"
  },
  {
    "hanzi": "铅印",
    "pinyin": "qiānyìn"
  },
  {
    "hanzi": "强弩之末",
    "pinyin": "qiángnǔzhīmò"
  }
]