[
  {
    "hanzi": "醒脑",
    "pinyin": "xǐngnǎo"
  },
  {
    "hanzi": "胸章",
    "pinyin": "xiōngzhāng"
  },
  {
    "hanzi": "秀逸",
    "pinyin": "xiùyì"
  },
  {
    "hanzi": "许婚",
    "pinyin": "xǔhūn"
  },
  {
    "hanzi": "旋转门",
    "pinyin": "xuánzhuǎnmén"
  },
  {
    "hanzi": "寻事",
    "pinyin": "xúnshì"
  },
  {
    "hanzi": "巡天",
    "pinyin": "xúntiān"
  },
  {
    "hanzi": "迅跑",
    "pinyin": "xùnpǎo"
  },
  {
    "hanzi": "牙周病",
    "pinyin": "yázhōubìng"
  },
  {
    "hanzi": "芽子",
    "pinyin": "yázi"
  },
  {
    "hanzi": "揠苗助长",
    "pinyin": "yàmiáozhùzhǎng"
  },
  {
    "hanzi": "言不及义",
    "pinyin": "yánbùjíyì"
  },
  {
    "hanzi": "言为心声",
    "pinyin": "yánwéixīnshēng"
  },
  {
    "hanzi": "夜光杯",
    "pinyin": "yèguāngbēi"
  },
  {
    "hanzi": "以远",
    "pinyin": "yǐyuǎn"
  },
  {
    "hanzi": "义母",
    "pinyin": "yìmǔ"
  },
  {
    "hanzi": "阴司",
    "pinyin": "yīnsī"
  },
  {
    "hanzi": "印张",
    "pinyin": "yìnzhāng"
  },
  {
    "hanzi": "影子内阁",
    "pinyin": "yǐngzinèigé"
  },
  {
    "hanzi": "优抚金",
    "pinyin": "yōufǔjīn"
  },
  {
    "hanzi": "有口难辩",
    "pinyin": "yǒukǒunánbiàn"
  },
  {
    "hanzi": "葬仪",
    "pinyin": "zàngyí"
  },
  {
    "hanzi": "枣泥",
    "pinyin": "zǎoní"
  },
  {
    "hanzi": "赠礼",
    "pinyin": "zènglǐ"
  },
  {
    "hanzi": "占卦",
    "pinyin": "zhānguà"
  },
  {
    "hanzi": "仗恃",
    "pinyin": "zhàngshì"
  },
  {
    "hanzi": "招之即来",
    "pinyin": "zhāozhījílái"
  },
  {
    "hanzi": "谪居",
    "pinyin": "zhéjū"
  },
  {
    "hanzi": "振幅",
    "pinyin": "zhènfú"
  },
  {
    "hanzi": "镇反",
    "pinyin": "zhènfǎn"
  },
  {
    "hanzi": "知更鸟",
    "pinyin": "zhīgēngniǎo"
  },
  {
    "hanzi": "知无不言，言无不尽",
    "pinyin": "zhīwúbùyán,yánwúbùjìn"
  },
  {
    "hanzi": "植物群落",
    "pinyin": "zhíwùqúnluò"
  },
  {
    "hanzi": "仲冬",
    "pinyin": "zhòngdōng"
  },
  {
    "hanzi": "众寡悬殊",
    "pinyin": "zhòngguǎxuánshū"
  },
  {
    "hanzi": "珠花",
    "pinyin": "zhūhuā"
  },
  {
    "hanzi": "主河道",
    "pinyin": "zhǔhédào"
  },
  {
    "hanzi": "专横跋扈",
    "pinyin": "zhuānhèngbáhù"
  },
  {
    "hanzi": "装填",
    "pinyin": "zhuāngtián"
  },
  {
    "hanzi": "装样子",
    "pinyin": "zhuāngyàngzi"
  },
  {
    "hanzi": "坠楼",
    "pinyin": "zhuìlóu"
  },
  {
    "hanzi": "自测",
    "pinyin": "zìcè"
  },
  {
    "hanzi": "自食其言",
    "pinyin": "zìshíqíyán"
  },
  {
    "hanzi": "自珍",
    "pinyin": "zìzhēn"
  },
  {
    "hanzi": "字书",
    "pinyin": "zìshū"
  },
  {
    "hanzi": "租子",
    "pinyin": "zūzi"
  },
  {
    "hanzi": "足月",
    "pinyin": "zúyuè"
  },
  {
    "hanzi": "左近",
    "pinyin": "zuǒjìn"
  },
  {
    "hanzi": "左轮",
    "pinyin": "zuǒlún"
  },
  {
    "hanzi": "坐怀不乱",
    "pinyin": "zuòhuáibùluàn"
  },
  {
    "hanzi": "阿门",
    "pinyin": "āmén"
  },
  {
    "hanzi": "熬出头",
    "pinyin": "áochūtóu"
  },
  {
    "hanzi": "八角形",
    "pinyin": "bājiǎoxíng"
  },
  {
    "hanzi": "耙地",
    "pinyin": "bàdì"
  },
  {
    "hanzi": "罢战",
    "pinyin": "bàzhàn"
  },
  {
    "hanzi": "白癜风",
    "pinyin": "báidiànfēng"
  },
  {
    "hanzi": "白卷",
    "pinyin": "báijuàn"
  },
  {
    "hanzi": "板胡",
    "pinyin": "bǎnhú"
  },
  {
    "hanzi": "绊儿",
    "pinyin": "bànr"
  },
  {
    "hanzi": "膀大腰圆",
    "pinyin": "bǎngdàyāoyuán"
  },
  {
    "hanzi": "保真",
    "pinyin": "bǎozhēn"
  },
  {
    "hanzi": "报验",
    "pinyin": "bàoyàn"
  },
  {
    "hanzi": "庇荫",
    "pinyin": "bìyìn"
  },
  {
    "hanzi": "壁垒森严",
    "pinyin": "bìlěisēnyán"
  },
  {
    "hanzi": "鞭辟入里",
    "pinyin": "biānpìrùlǐ"
  },
  {
    "hanzi": "表册",
    "pinyin": "biǎocè"
  },
  {
    "hanzi": "兵役制",
    "pinyin": "bīngyìzhì"
  },
  {
    "hanzi": "薄酒",
    "pinyin": "bójiǔ"
  },
  {
    "hanzi": "补液",
    "pinyin": "bǔyè"
  },
  {
    "hanzi": "不时之需",
    "pinyin": "bùshízhīxū"
  },
  {
    "hanzi": "草字",
    "pinyin": "cǎozì"
  },
  {
    "hanzi": "茬口",
    "pinyin": "chákǒu"
  },
  {
    "hanzi": "豺狗",
    "pinyin": "cháigǒu"
  },
  {
    "hanzi": "吵骂",
    "pinyin": "chǎomà"
  },
  {
    "hanzi": "澄净",
    "pinyin": "chéngjìng"
  },
  {
    "hanzi": "虫眼",
    "pinyin": "chóngyǎn"
  },
  {
    "hanzi": "酬酢",
    "pinyin": "chóuzuò"
  },
  {
    "hanzi": "踌躇不前",
    "pinyin": "chóuchúbùqián"
  },
  {
    "hanzi": "出芽",
    "pinyin": "chūyá"
  },
  {
    "hanzi": "串演",
    "pinyin": "chuànyǎn"
  },
  {
    "hanzi": "床榻",
    "pinyin": "chuángtà"
  },
  {
    "hanzi": "从难",
    "pinyin": "cóngnán"
  },
  {
    "hanzi": "锉刀",
    "pinyin": "cuòdāo"
  },
  {
    "hanzi": "错车",
    "pinyin": "cuòchē"
  },
  {
    "hanzi": "错待",
    "pinyin": "cuòdài"
  },
  {
    "hanzi": "搭帮",
    "pinyin": "dābāng"
  },
  {
    "hanzi": "大晴天",
    "pinyin": "dàqíngtiān"
  },
  {
    "hanzi": "大舌头",
    "pinyin": "dàshétou"
  },
  {
    "hanzi": "大治",
    "pinyin": "dàzhì"
  },
  {
    "hanzi": "代销店",
    "pinyin": "dàixiāodiàn"
  },
  {
    "hanzi": "代议制",
    "pinyin": "dàiyìzhì"
  },
  {
    "hanzi": "单相",
    "pinyin": "dānxiàng"
  },
  {
    "hanzi": "导诊",
    "pinyin": "dǎozhěn"
  },
  {
    "hanzi": "捣鼓",
    "pinyin": "dǎogu"
  },
  {
    "hanzi": "倒账",
    "pinyin": "dǎozhàng"
  },
  {
    "hanzi": "低等动物",
    "pinyin": "dīděngdòngwù"
  },
  {
    "hanzi": "滴漏",
    "pinyin": "dīlòu"
  },
  {
    "hanzi": "地脉",
    "pinyin": "dìmài"
  },
  {
    "hanzi": "点射",
    "pinyin": "diǎnshè"
  },
  {
    "hanzi": "踮脚",
    "pinyin": "diǎnjiǎo"
  },
  {
    "hanzi": "电力线",
    "pinyin": "diànl'ìxiàn"
  },
  {
    "hanzi": "动刑",
    "pinyin": "dòngxíng"
  },
  {
    "hanzi": "度荒",
    "pinyin": "dùhuāng"
  },
  {
    "hanzi": "对头",
    "pinyin": "duìtou"
  },
  {
    "hanzi": "钝器",
    "pinyin": "dùnqì"
  },
  {
    "hanzi": "多一半",
    "pinyin": "duōyībàn"
  },
  {
    "hanzi": "娥眉",
    "pinyin": "éméi"
  },
  {
    "hanzi": "恩重如山",
    "pinyin": "ēnzhòngrúshān"
  },
  {
    "hanzi": "发喘",
    "pinyin": "fāchuǎn"
  },
  {
    "hanzi": "发蒙",
    "pinyin": "fāméng"
  },
  {
    "hanzi": "凡间",
    "pinyin": "fánjiān"
  },
  {
    "hanzi": "繁缛",
    "pinyin": "fánrù"
  },
  {
    "hanzi": "泛论",
    "pinyin": "fànlùn"
  },
  {
    "hanzi": "纺织娘",
    "pinyin": "fǎngzhīniáng"
  },
  {
    "hanzi": "飞贼",
    "pinyin": "fēizéi"
  },
  {
    "hanzi": "非婚生",
    "pinyin": "fēihūnshēng"
  },
  {
    "hanzi": "肥皂剧",
    "pinyin": "féizàojù"
  },
  {
    "hanzi": "榧子",
    "pinyin": "fěizi"
  },
  {
    "hanzi": "粉盒",
    "pinyin": "fěnhé"
  },
  {
    "hanzi": "风雨如磐",
    "pinyin": "fēngyǔrúpán"
  },
  {
    "hanzi": "风疹",
    "pinyin": "fēngzhěn"
  },
  {
    "hanzi": "凤梨",
    "pinyin": "fènglí"
  },
  {
    "hanzi": "改扮",
    "pinyin": "gǎibàn"
  },
  {
    "hanzi": "改线",
    "pinyin": "gǎixiàn"
  },
  {
    "hanzi": "盖印",
    "pinyin": "gàiyìn"
  },
  {
    "hanzi": "干酪",
    "pinyin": "gānlào"
  },
  {
    "hanzi": "赶会",
    "pinyin": "gǎnhuì"
  },
  {
    "hanzi": "搞臭",
    "pinyin": "gǎochòu"
  },
  {
    "hanzi": "勾连",
    "pinyin": "gōulián"
  },
  {
    "hanzi": "钩虫",
    "pinyin": "gōuchóng"
  },
  {
    "hanzi": "苟合",
    "pinyin": "gǒuhé"
  },
  {
    "hanzi": "够劲儿",
    "pinyin": "gòujìnr"
  },
  {
    "hanzi": "孤魂野鬼",
    "pinyin": "gūhúnyěguǐ"
  },
  {
    "hanzi": "股评",
    "pinyin": "gǔpíng"
  },
  {
    "hanzi": "瓜田李下",
    "pinyin": "guātiánlǐxià"
  },
  {
    "hanzi": "广柑",
    "pinyin": "guǎnggān"
  },
  {
    "hanzi": "广寒宫",
    "pinyin": "guǎnghángōng"
  },
  {
    "hanzi": "硅藻",
    "pinyin": "guīzǎo"
  },
  {
    "hanzi": "裙带风",
    "pinyin": "qúndàifēng"
  },
  {
    "hanzi": "果糖",
    "pinyin": "guǒtáng"
  },
  {
    "hanzi": "汗淋淋",
    "pinyin": "hànlínlín"
  },
  {
    "hanzi": "和洽",
    "pinyin": "héqià"
  },
  {
    "hanzi": "狠话",
    "pinyin": "hěnhuà"
  },
  {
    "hanzi": "猴戏",
    "pinyin": "hóuxì"
  },
  {
    "hanzi": "花俏",
    "pinyin": "huāqiào"
  },
  {
    "hanzi": "花饰",
    "pinyin": "huāshì"
  },
  {
    "hanzi": "花砖",
    "pinyin": "huāzhuān"
  },
  {
    "hanzi": "话家常",
    "pinyin": "huàjiācháng"
  },
  {
    "hanzi": "唤头",
    "pinyin": "huàntou"
  },
  {
    "hanzi": "昏话",
    "pinyin": "hūnhuà"
  },
  {
    "hanzi": "混子",
    "pinyin": "hùnzi"
  },
  {
    "hanzi": "祸殃",
    "pinyin": "huòyāng"
  },
  {
    "hanzi": "惑乱",
    "pinyin": "huòluàn"
  },
  {
    "hanzi": "容姿",
    "pinyin": "róngzī"
  },
  {
    "hanzi": "机心",
    "pinyin": "jīxīn"
  },
  {
    "hanzi": "鸡毛掸子",
    "pinyin": "jīmáodǎnzi"
  },
  {
    "hanzi": "记时",
    "pinyin": "jìshí"
  },
  {
    "hanzi": "家常饭",
    "pinyin": "jiāchángfàn"
  },
  {
    "hanzi": "发贱",
    "pinyin": "fājiàn"
  },
  {
    "hanzi": "奸猾",
    "pinyin": "jiānhuá"
  },
  {
    "hanzi": "浆汁",
    "pinyin": "jiāngzhī"
  },
  {
    "hanzi": "焦煤",
    "pinyin": "jiāoméi"
  },
  {
    "hanzi": "角钢",
    "pinyin": "jiǎogāng"
  },
  {
    "hanzi": "狡赖",
    "pinyin": "jiǎolài"
  },
  {
    "hanzi": "教民",
    "pinyin": "jiàomín"
  },
  {
    "hanzi": "接火",
    "pinyin": "jiēhuǒ"
  },
  {
    "hanzi": "接转",
    "pinyin": "jiēzhuǎn"
  },
  {
    "hanzi": "街垒",
    "pinyin": "jiēlěi"
  },
  {
    "hanzi": "节略",
    "pinyin": "jiélüè"
  },
  {
    "hanzi": "遐迩闻名",
    "pinyin": "xiá'ěrwénmíng"
  },
  {
    "hanzi": "老交情",
    "pinyin": "lǎojiāoqing"
  },
  {
    "hanzi": "结仇",
    "pinyin": "jiéchóu"
  },
  {
    "hanzi": "借方",
    "pinyin": "jièfāng"
  },
  {
    "hanzi": "冒认",
    "pinyin": "màorèn"
  },
  {
    "hanzi": "具保",
    "pinyin": "jùbǎo"
  },
  {
    "hanzi": "金本位",
    "pinyin": "jīnběnwèi"
  },
  {
    "hanzi": "金桂",
    "pinyin": "jīnguì"
  },
  {
    "hanzi": "金融寡头",
    "pinyin": "jīnróngguǎtóu"
  },
  {
    "hanzi": "紧追",
    "pinyin": "jǐnzhuī"
  },
  {
    "hanzi": "京白",
    "pinyin": "jīngbái"
  },
  {
    "hanzi": "精密度",
    "pinyin": "jīngmìdù"
  },
  {
    "hanzi": "绝命书",
    "pinyin": "juémìngshū"
  },
  {
    "hanzi": "军棋",
    "pinyin": "jūnqí"
  },
  {
    "hanzi": "苦境",
    "pinyin": "kǔjìng"
  },
  {
    "hanzi": "阔叶树",
    "pinyin": "kuòyèshù"
  },
  {
    "hanzi": "丢份",
    "pinyin": "diūfèn"
  },
  {
    "hanzi": "聘约",
    "pinyin": "pìnyuē"
  },
  {
    "hanzi": "拉丁舞",
    "pinyin": "lādīngwǔ"
  },
  {
    "hanzi": "辣椒油",
    "pinyin": "làjiāoyóu"
  },
  {
    "hanzi": "蓝靛",
    "pinyin": "lándiàn"
  },
  {
    "hanzi": "老虎灶",
    "pinyin": "lǎohǔzào"
  },
  {
    "hanzi": "老脑筋",
    "pinyin": "lǎonǎojīn"
  },
  {
    "hanzi": "冷水澡",
    "pinyin": "lěngshuǐzǎo"
  },
  {
    "hanzi": "凉面",
    "pinyin": "liángmiàn"
  },
  {
    "hanzi": "临风",
    "pinyin": "línfēng"
  },
  {
    "hanzi": "灵塔",
    "pinyin": "língtǎ"
  },
  {
    "hanzi": "网关",
    "pinyin": "wǎngguān"
  },
  {
    "hanzi": "书眉",
    "pinyin": "shūméi"
  },
  {
    "hanzi": "溜索",
    "pinyin": "liūsuǒ"
  },
  {
    "hanzi": "流里流气",
    "pinyin": "liúliliúqì"
  },
  {
    "hanzi": "龙争虎斗",
    "pinyin": "lóngzhēnghǔdòu"
  },
  {
    "hanzi": "笼养",
    "pinyin": "lóngyǎng"
  },
  {
    "hanzi": "炉具",
    "pinyin": "lújù"
  },
  {
    "hanzi": "路遇",
    "pinyin": "lùyù"
  },
  {
    "hanzi": "乱伦",
    "pinyin": "luànlún"
  },
  {
    "hanzi": "落英",
    "pinyin": "luòyīng"
  },
  {
    "hanzi": "麻醉师",
    "pinyin": "mázuìshī"
  },
  {
    "hanzi": "毛衫",
    "pinyin": "máoshān"
  },
  {
    "hanzi": "眉笔",
    "pinyin": "méibǐ"
  },
  {
    "hanzi": "美术字",
    "pinyin": "měishùzì"
  },
  {
    "hanzi": "魅惑",
    "pinyin": "mèihuò"
  },
  {
    "hanzi": "门岗",
    "pinyin": "méngǎng"
  },
  {
    "hanzi": "蒙师",
    "pinyin": "méngshī"
  },
  {
    "hanzi": "棉织品",
    "pinyin": "miánzhīpǐn"
  },
  {
    "hanzi": "面包房",
    "pinyin": "miànbāofáng"
  },
  {
    "hanzi": "名讳",
    "pinyin": "mínghuì"
  },
  {
    "hanzi": "明断",
    "pinyin": "míngduàn"
  },
  {
    "hanzi": "明沟",
    "pinyin": "mínggōu"
  },
  {
    "hanzi": "明面",
    "pinyin": "míngmiàn"
  },
  {
    "hanzi": "哲言",
    "pinyin": "zhéyán"
  },
  {
    "hanzi": "磨叨",
    "pinyin": "mòdao"
  },
  {
    "hanzi": "木樨",
    "pinyin": "mùxi"
  },
  {
    "hanzi": "目光如炬",
    "pinyin": "mùguāngrújù"
  },
  {
    "hanzi": "拿架子",
    "pinyin": "nájiàzi"
  },
  {
    "hanzi": "三级片",
    "pinyin": "sānjípiàn"
  },
  {
    "hanzi": "内胎",
    "pinyin": "nèitāi"
  },
  {
    "hanzi": "排挡",
    "pinyin": "páidǎng"
  },
  {
    "hanzi": "排毒",
    "pinyin": "páidú"
  },
  {
    "hanzi": "旁支",
    "pinyin": "pángzhī"
  },
  {
    "hanzi": "胖墩墩",
    "pinyin": "pàngdūndūn"
  },
  {
    "hanzi": "跑单帮",
    "pinyin": "pǎodānbāng"
  },
  {
    "hanzi": "捧哏",
    "pinyin": "pěnggén"
  },
  {
    "hanzi": "偏劳",
    "pinyin": "piānláo"
  },
  {
    "hanzi": "妄议",
    "pinyin": "wàngyì"
  },
  {
    "hanzi": "平底鞋",
    "pinyin": "píngdǐxié"
  },
  {
    "hanzi": "难侨",
    "pinyin": "nànqiáo"
  },
  {
    "hanzi": "平年",
    "pinyin": "píngnián"
  },
  {
    "hanzi": "冗官",
    "pinyin": "rǒngguān"
  },
  {
    "hanzi": "评标",
    "pinyin": "píngbiāo"
  },
  {
    "hanzi": "铺砌",
    "pinyin": "pūqì"
  },
  {
    "hanzi": "铺保",
    "pinyin": "pùbǎo"
  },
  {
    "hanzi": "七巧板",
    "pinyin": "qīqiǎobǎn"
  },
  {
    "hanzi": "妻舅",
    "pinyin": "qījiù"
  },
  {
    "hanzi": "欺哄",
    "pinyin": "qīhǒng"
  },
  {
    "hanzi": "欺人之谈",
    "pinyin": "qīrénzhītán"
  },
  {
    "hanzi": "荞面",
    "pinyin": "qiáomiàn"
  },
  {
    "hanzi": "巧匠",
    "pinyin": "qiǎojiàng"
  },
  {
    "hanzi": "轻贱",
    "pinyin": "qīngjiàn"
  },
  {
    "hanzi": "轻扬",
    "pinyin": "qīngyáng"
  },
  {
    "hanzi": "清平",
    "pinyin": "qīngpíng"
  },
  {
    "hanzi": "囚衣",
    "pinyin": "qiúyī"
  },
  {
    "hanzi": "犬儒",
    "pinyin": "quǎnrú"
  },
  {
    "hanzi": "犬牙",
    "pinyin": "quǎnyá"
  },
  {
    "hanzi": "缺勤",
    "pinyin": "quēqín"
  },
  {
    "hanzi": "群婚",
    "pinyin": "qúnhūn"
  },
  {
    "hanzi": "人机对话",
    "pinyin": "rénjīduìhuà"
  },
  {
    "hanzi": "人精",
    "pinyin": "rénjīng"
  },
  {
    "hanzi": "稔熟",
    "pinyin": "rěnshú"
  },
  {
    "hanzi": "扔弃",
    "pinyin": "rēngqì"
  },
  {
    "hanzi": "荣誉军人",
    "pinyin": "róngyùjūnrén"
  },
  {
    "hanzi": "撒赖",
    "pinyin": "sālài"
  },
  {
    "hanzi": "臊子",
    "pinyin": "sàozi"
  },
  {
    "hanzi": "杀人如麻",
    "pinyin": "shārénrúmá"
  },
  {
    "hanzi": "沙发床",
    "pinyin": "shāfāchuáng"
  },
  {
    "hanzi": "山南海北",
    "pinyin": "shānnánhǎiběi"
  },
  {
    "hanzi": "删削",
    "pinyin": "shānxuē"
  },
  {
    "hanzi": "苫布",
    "pinyin": "shànbù"
  },
  {
    "hanzi": "折本",
    "pinyin": "shéběn"
  },
  {
    "hanzi": "社会工作",
    "pinyin": "shèhuìgōngzuò"
  },
  {
    "hanzi": "摄生",
    "pinyin": "shèshēng"
  },
  {
    "hanzi": "深翻",
    "pinyin": "shēnfān"
  },
  {
    "hanzi": "肾结石",
    "pinyin": "shènjiéshí"
  },
  {
    "hanzi": "生土",
    "pinyin": "shēngtǔ"
  },
  {
    "hanzi": "失密",
    "pinyin": "shīmì"
  },
  {
    "hanzi": "狮子狗",
    "pinyin": "shīzigǒu"
  },
  {
    "hanzi": "施威",
    "pinyin": "shīwēi"
  },
  {
    "hanzi": "食补",
    "pinyin": "shíbǔ"
  },
  {
    "hanzi": "食古不化",
    "pinyin": "shígǔbùhuà"
  },
  {
    "hanzi": "恃才傲物",
    "pinyin": "shìcáiàowù"
  },
  {
    "hanzi": "收口",
    "pinyin": "shōukǒu"
  },
  {
    "hanzi": "受听",
    "pinyin": "shòutīng"
  },
  {
    "hanzi": "舒卷",
    "pinyin": "shūjuǎn"
  },
  {
    "hanzi": "束手束脚",
    "pinyin": "shùshǒushùjiǎo"
  },
  {
    "hanzi": "刷拉",
    "pinyin": "shuālā"
  },
  {
    "hanzi": "耍无赖",
    "pinyin": "shuǎwúlài"
  },
  {
    "hanzi": "双氧水",
    "pinyin": "shuāngyǎngshuǐ"
  },
  {
    "hanzi": "水浮莲",
    "pinyin": "shuǐfúlián"
  },
  {
    "hanzi": "顺次",
    "pinyin": "shùncì"
  },
  {
    "hanzi": "说东道西",
    "pinyin": "shuōdōngdàoxī"
  },
  {
    "hanzi": "硕果仅存",
    "pinyin": "shuòguǒjǐncún"
  },
  {
    "hanzi": "私房话",
    "pinyin": "sīfánghuà"
  },
  {
    "hanzi": "死火山",
    "pinyin": "sǐhuǒshān"
  },
  {
    "hanzi": "死胎",
    "pinyin": "sǐtāi"
  },
  {
    "hanzi": "四大皆空",
    "pinyin": "sìdàjiēkōng"
  },
  {
    "hanzi": "松花蛋",
    "pinyin": "sōnghuādàn"
  },
  {
    "hanzi": "耸身",
    "pinyin": "sǒngshēn"
  },
  {
    "hanzi": "酥麻",
    "pinyin": "sūmá"
  },
  {
    "hanzi": "塑钢",
    "pinyin": "sùgāng"
  },
  {
    "hanzi": "太阳地儿",
    "pinyin": "tàiyángdìr"
  },
  {
    "hanzi": "炭火盆",
    "pinyin": "tànhuǒpén"
  },
  {
    "hanzi": "套马杆",
    "pinyin": "tàomǎgān"
  },
  {
    "hanzi": "天青",
    "pinyin": "tiānqīng"
  },
  {
    "hanzi": "天渊之别",
    "pinyin": "tiānyuānzhībié"
  },
  {
    "hanzi": "田契",
    "pinyin": "tiánqì"
  },
  {
    "hanzi": "挑刺儿",
    "pinyin": "tiāocìr"
  },
  {
    "hanzi": "铁蚕豆",
    "pinyin": "tiěcándòu"
  },
  {
    "hanzi": "庭训",
    "pinyin": "tíngxùn"
  },
  {
    "hanzi": "同出一辙",
    "pinyin": "tóngchūyīzhé"
  },
  {
    "hanzi": "同犯",
    "pinyin": "tóngfàn"
  },
  {
    "hanzi": "彤云",
    "pinyin": "tóngyún"
  },
  {
    "hanzi": "头班车",
    "pinyin": "tóubānchē"
  },
  {
    "hanzi": "土包",
    "pinyin": "tǔbāo"
  },
  {
    "hanzi": "拖家带口",
    "pinyin": "tuōjiādàikǒu"
  },
  {
    "hanzi": "望风而逃",
    "pinyin": "wàngfēng'értáo"
  },
  {
    "hanzi": "伪钞",
    "pinyin": "wěichāo"
  },
  {
    "hanzi": "瘟病",
    "pinyin": "wēnbìng"
  },
  {
    "hanzi": "文场",
    "pinyin": "wénchǎng"
  },
  {
    "hanzi": "屋基",
    "pinyin": "wūjī"
  },
  {
    "hanzi": "无名之辈",
    "pinyin": "wúmíngzhībèi"
  },
  {
    "hanzi": "无奈何",
    "pinyin": "wúnàihé"
  },
  {
    "hanzi": "物换星移",
    "pinyin": "wùhuànxīngyí"
  },
  {
    "hanzi": "嘻闹",
    "pinyin": "xīnào"
  },
  {
    "hanzi": "下箸",
    "pinyin": "xiàzhù"
  },
  {
    "hanzi": "下装",
    "pinyin": "xiàzhuāng"
  },
  {
    "hanzi": "纤毫",
    "pinyin": "xiānháo"
  },
  {
    "hanzi": "鲜货",
    "pinyin": "xiānhuò"
  },
  {
    "hanzi": "闲杂人员",
    "pinyin": "xiánzárényuán"
  },
  {
    "hanzi": "现况",
    "pinyin": "xiànkuàng"
  },
  {
    "hanzi": "线毯",
    "pinyin": "xiàntǎn"
  },
  {
    "hanzi": "响晴",
    "pinyin": "xiǎngqíng"
  },
  {
    "hanzi": "相术",
    "pinyin": "xiàngshù"
  },
  {
    "hanzi": "硝酸甘油",
    "pinyin": "xiāosuāngānyóu"
  },
  {
    "hanzi": "小本经营",
    "pinyin": "xiǎoběnjīngyíng"
  },
  {
    "hanzi": "小肚鸡肠",
    "pinyin": "xiǎodùjīcháng"
  },
  {
    "hanzi": "小钢炮",
    "pinyin": "xiǎogāngpào"
  },
  {
    "hanzi": "小气鬼",
    "pinyin": "xiǎoqìguǐ"
  },
  {
    "hanzi": "小篆",
    "pinyin": "xiǎozhuàn"
  },
  {
    "hanzi": "邪乎",
    "pinyin": "xiéhu"
  },
  {
    "hanzi": "斜角",
    "pinyin": "xiéjiǎo"
  },
  {
    "hanzi": "携家带口",
    "pinyin": "xiéjiādàikǒu"
  },
  {
    "hanzi": "辛苦费",
    "pinyin": "xīnkǔfèi"
  },
  {
    "hanzi": "欣悉",
    "pinyin": "xīnxī"
  },
  {
    "hanzi": "雄姿英发",
    "pinyin": "xióngzīyīngfā"
  },
  {
    "hanzi": "羞恼",
    "pinyin": "xiūnǎo"
  },
  {
    "hanzi": "畜养",
    "pinyin": "xùyǎng"
  },
  {
    "hanzi": "蓄势待发",
    "pinyin": "xùshìdàifā"
  },
  {
    "hanzi": "血海深仇",
    "pinyin": "xuèhǎishēnchóu"
  },
  {
    "hanzi": "勋劳",
    "pinyin": "xūnláo"
  },
  {
    "hanzi": "勋业",
    "pinyin": "xūnyè"
  },
  {
    "hanzi": "寻获",
    "pinyin": "xúnhuò"
  },
  {
    "hanzi": "正经八百",
    "pinyin": "zhèngjīngbābǎi"
  },
  {
    "hanzi": "雅气",
    "pinyin": "yǎqì"
  },
  {
    "hanzi": "烟贩",
    "pinyin": "yānfàn"
  },
  {
    "hanzi": "雁过拔毛",
    "pinyin": "yànguòbámáo"
  },
  {
    "hanzi": "药面",
    "pinyin": "yàomiàn"
  },
  {
    "hanzi": "夜不闭户",
    "pinyin": "yèbùbìhù"
  },
  {
    "hanzi": "衣不蔽体",
    "pinyin": "yībùbìtǐ"
  },
  {
    "hanzi": "遗缺",
    "pinyin": "yíquē"
  },
  {
    "hanzi": "易帜",
    "pinyin": "yìzhì"
  },
  {
    "hanzi": "银粉",
    "pinyin": "yínfěn"
  },
  {
    "hanzi": "引论",
    "pinyin": "yǐnlùn"
  },
  {
    "hanzi": "引蛇出洞",
    "pinyin": "yǐnshéchūdòng"
  },
  {
    "hanzi": "隐形眼镜",
    "pinyin": "yǐnxíngyǎnjìng"
  },
  {
    "hanzi": "瘾头",
    "pinyin": "yǐntóu"
  },
  {
    "hanzi": "印欧语",
    "pinyin": "yìnōuyǔ"
  },
  {
    "hanzi": "缨子",
    "pinyin": "yīngzi"
  },
  {
    "hanzi": "蝇子",
    "pinyin": "yíngzi"
  },
  {
    "hanzi": "影带",
    "pinyin": "yǐngdài"
  },
  {
    "hanzi": "硬通货",
    "pinyin": "yìngtōnghuò"
  },
  {
    "hanzi": "油花",
    "pinyin": "yóuhuā"
  },
  {
    "hanzi": "有隙可乘",
    "pinyin": "yǒuxìkěchéng"
  },
  {
    "hanzi": "诱拐",
    "pinyin": "yòuguǎi"
  },
  {
    "hanzi": "余剩",
    "pinyin": "yúshèng"
  },
  {
    "hanzi": "鱼腥草",
    "pinyin": "yúxīngcǎo"
  },
  {
    "hanzi": "郁郁苍苍",
    "pinyin": "yùyùcāngcāng"
  },
  {
    "hanzi": "杂项",
    "pinyin": "záxiàng"
  },
  {
    "hanzi": "栽插",
    "pinyin": "zāichā"
  },
  {
    "hanzi": "糟糠",
    "pinyin": "zāokāng"
  },
  {
    "hanzi": "糟心",
    "pinyin": "zāoxīn"
  },
  {
    "hanzi": "早车",
    "pinyin": "zǎochē"
  },
  {
    "hanzi": "诈取",
    "pinyin": "zhàqǔ"
  },
  {
    "hanzi": "站台票",
    "pinyin": "zhàntáipiào"
  },
  {
    "hanzi": "招式",
    "pinyin": "zhāoshì"
  },
  {
    "hanzi": "针叶树",
    "pinyin": "zhēnyèshù"
  },
  {
    "hanzi": "正当年",
    "pinyin": "zhèngdāngnián"
  },
  {
    "hanzi": "正经话",
    "pinyin": "zhèngjīnghuà"
  },
  {
    "hanzi": "正犯",
    "pinyin": "zhèngfàn"
  },
  {
    "hanzi": "支渠",
    "pinyin": "zhīqú"
  },
  {
    "hanzi": "支应",
    "pinyin": "zhīyìng"
  },
  {
    "hanzi": "直肠子",
    "pinyin": "zhíchángzi"
  },
  {
    "hanzi": "直书",
    "pinyin": "zhíshū"
  },
  {
    "hanzi": "中继线",
    "pinyin": "zhōngjìxiàn"
  },
  {
    "hanzi": "钟灵毓秀",
    "pinyin": "zhōnglíngyùxiù"
  },
  {
    "hanzi": "重办",
    "pinyin": "zhòngbàn"
  },
  {
    "hanzi": "伫候",
    "pinyin": "zhùhòu"
  },
  {
    "hanzi": "注文",
    "pinyin": "zhùwén"
  },
  {
    "hanzi": "篆文",
    "pinyin": "zhuànwén"
  },
  {
    "hanzi": "追歼",
    "pinyin": "zhuījiān"
  },
  {
    "hanzi": "灼见",
    "pinyin": "zhuójiàn"
  },
  {
    "hanzi": "浊世",
    "pinyin": "zhuóshì"
  },
  {
    "hanzi": "祖产",
    "pinyin": "zǔchǎn"
  },
  {
    "hanzi": "罪不容诛",
    "pinyin": "zuìbùróngzhū"
  },
  {
    "hanzi": "坐探",
    "pinyin": "zuòtàn"
  },
  {
    "hanzi": "安全阀",
    "pinyin": "ānquánfá"
  },
  {
    "hanzi": "暗记",
    "pinyin": "ànjì"
  },
  {
    "hanzi": "暗器",
    "pinyin": "ànqì"
  },
  {
    "hanzi": "霸王鞭",
    "pinyin": "bàwángbiān"
  },
  {
    "hanzi": "白食",
    "pinyin": "báishí"
  },
  {
    "hanzi": "拜领",
    "pinyin": "bàilǐng"
  },
  {
    "hanzi": "帮佣",
    "pinyin": "bāngyōng"
  },
  {
    "hanzi": "绑带",
    "pinyin": "bǎngdài"
  },
  {
    "hanzi": "包退",
    "pinyin": "bāotuì"
  },
  {
    "hanzi": "保媒",
    "pinyin": "bǎoméi"
  },
  {
    "hanzi": "保险带",
    "pinyin": "bǎoxiǎndài"
  },
  {
    "hanzi": "悖谬",
    "pinyin": "bèimiù"
  },
  {
    "hanzi": "鄙意",
    "pinyin": "bǐyì"
  },
  {
    "hanzi": "箅子",
    "pinyin": "bìzi"
  },
  {
    "hanzi": "臂肘",
    "pinyin": "bìzhǒu"
  },
  {
    "hanzi": "飙车",
    "pinyin": "biāochē"
  },
  {
    "hanzi": "博古通今",
    "pinyin": "bógǔtōngjīn"
  },
  {
    "hanzi": "博闻强记",
    "pinyin": "bówénqiángjì"
  },
  {
    "hanzi": "操琴",
    "pinyin": "cāoqín"
  },
  {
    "hanzi": "草酸",
    "pinyin": "cǎosuān"
  },
  {
    "hanzi": "策励",
    "pinyin": "cèlì"
  },
  {
    "hanzi": "茶油",
    "pinyin": "cháyóu"
  },
  {
    "hanzi": "禅机",
    "pinyin": "chánjī"
  },
  {
    "hanzi": "颤悠",
    "pinyin": "chànyou"
  },
  {
    "hanzi": "长策",
    "pinyin": "chángcè"
  },
  {
    "hanzi": "车前草",
    "pinyin": "chēqiáncǎo"
  },
  {
    "hanzi": "陈尸",
    "pinyin": "chénshī"
  },
  {
    "hanzi": "撑门面",
    "pinyin": "chēngménmian"
  },
  {
    "hanzi": "承先启后",
    "pinyin": "chéngxiānqǐhòu"
  },
  {
    "hanzi": "吃里爬外",
    "pinyin": "chīlǐpáwài"
  },
  {
    "hanzi": "筹募",
    "pinyin": "chóumù"
  },
  {
    "hanzi": "出摊儿",
    "pinyin": "chūtānr"
  },
  {
    "hanzi": "初会",
    "pinyin": "chūhuì"
  },
  {
    "hanzi": "除虫菊",
    "pinyin": "chúchóngjú"
  },
  {
    "hanzi": "楚剧",
    "pinyin": "chǔjù"
  },
  {
    "hanzi": "创税",
    "pinyin": "chuàngshuì"
  },
  {
    "hanzi": "垂直线",
    "pinyin": "chuízhíxiàn"
  },
  {
    "hanzi": "醇美",
    "pinyin": "chúnměi"
  },
  {
    "hanzi": "刺痒",
    "pinyin": "cìyang"
  },
  {
    "hanzi": "凑份子",
    "pinyin": "còufènzi"
  },
  {
    "hanzi": "猝发",
    "pinyin": "cùfā"
  },
  {
    "hanzi": "醋劲儿",
    "pinyin": "cùjìnr"
  },
  {
    "hanzi": "打呃",
    "pinyin": "dǎ'è"
  },
  {
    "hanzi": "打卡",
    "pinyin": "dǎkǎ"
  },
  {
    "hanzi": "打擂台",
    "pinyin": "dǎlèitái"
  },
  {
    "hanzi": "打拍子",
    "pinyin": "dǎpāizi"
  },
  {
    "hanzi": "打入冷宫",
    "pinyin": "dǎrùlěnggōng"
  },
  {
    "hanzi": "打印纸",
    "pinyin": "dǎyìnzhǐ"
  },
  {
    "hanzi": "带菌",
    "pinyin": "dàijūn"
  },
  {
    "hanzi": "待查",
    "pinyin": "dàichá"
  },
  {
    "hanzi": "待续",
    "pinyin": "dàixù"
  },
  {
    "hanzi": "戴绿帽",
    "pinyin": "dàilǜmào"
  },
  {
    "hanzi": "单元门",
    "pinyin": "dānyuánmén"
  },
  {
    "hanzi": "淡而无味",
    "pinyin": "dàn'érwúwèi"
  },
  {
    "hanzi": "弹无虚发",
    "pinyin": "dànwúxūfā"
  },
  {
    "hanzi": "到庭",
    "pinyin": "dàotíng"
  },
  {
    "hanzi": "倒栽葱",
    "pinyin": "dàozāicōng"
  },
  {
    "hanzi": "低幼",
    "pinyin": "dīyòu"
  },
  {
    "hanzi": "第二梯队",
    "pinyin": "dìèrtīduì"
  },
  {
    "hanzi": "吊床",
    "pinyin": "diàochuáng"
  },
  {
    "hanzi": "吊兰",
    "pinyin": "diàolán"
  },
  {
    "hanzi": "顶班",
    "pinyin": "dǐngbān"
  },
  {
    "hanzi": "动兵",
    "pinyin": "dòngbīng"
  },
  {
    "hanzi": "抖威风",
    "pinyin": "dǒuwēifēng"
  },
  {
    "hanzi": "豆绿",
    "pinyin": "dòulǜ"
  },
  {
    "hanzi": "逗哏",
    "pinyin": "dòugén"
  },
  {
    "hanzi": "髑髅",
    "pinyin": "dúlóu"
  },
  {
    "hanzi": "堵心",
    "pinyin": "dǔxīn"
  },
  {
    "hanzi": "短不了",
    "pinyin": "duǎnbuliǎo"
  },
  {
    "hanzi": "断顿",
    "pinyin": "duàndùn"
  },
  {
    "hanzi": "遁词",
    "pinyin": "dùncí"
  },
  {
    "hanzi": "鄂温克族",
    "pinyin": "èwēnkèzú"
  },
  {
    "hanzi": "翻刻",
    "pinyin": "fānkè"
  },
  {
    "hanzi": "芳馨",
    "pinyin": "fāngxīn"
  },
  {
    "hanzi": "放怀",
    "pinyin": "fànghuái"
  },
  {
    "hanzi": "飞泻",
    "pinyin": "fēixiè"
  },
  {
    "hanzi": "非同凡响",
    "pinyin": "fēitóngfánxiǎng"
  },
  {
    "hanzi": "丰歉",
    "pinyin": "fēngqiàn"
  },
  {
    "hanzi": "风烟",
    "pinyin": "fēngyān"
  },
  {
    "hanzi": "风钻",
    "pinyin": "fēngzuàn"
  },
  {
    "hanzi": "凤尾竹",
    "pinyin": "fèngwěizhú"
  },
  {
    "hanzi": "奉令",
    "pinyin": "fènglìng"
  },
  {
    "hanzi": "抚琴",
    "pinyin": "fǔqín"
  },
  {
    "hanzi": "妇产",
    "pinyin": "fùchǎn"
  },
  {
    "hanzi": "干亲家",
    "pinyin": "gānqìngjia"
  },
  {
    "hanzi": "赶任务",
    "pinyin": "gǎnrènwù"
  },
  {
    "hanzi": "感戴",
    "pinyin": "gǎndài"
  },
  {
    "hanzi": "感叹号",
    "pinyin": "gǎntànhào"
  },
  {
    "hanzi": "钢圈",
    "pinyin": "gāngquān"
  },
  {
    "hanzi": "高阁",
    "pinyin": "gāogé"
  },
  {
    "hanzi": "搞头",
    "pinyin": "gǎotou"
  },
  {
    "hanzi": "歌咏队",
    "pinyin": "gēyǒngduì"
  },
  {
    "hanzi": "工价",
    "pinyin": "gōngjià"
  },
  {
    "hanzi": "工间操",
    "pinyin": "gōngjiāncāo"
  },
  {
    "hanzi": "攻无不克",
    "pinyin": "gōngwúbùkè"
  },
  {
    "hanzi": "宫颈",
    "pinyin": "gōngjǐng"
  },
  {
    "hanzi": "古文献",
    "pinyin": "gǔwénxiàn"
  }
]